{"instance": "small_free_004_20x20_20_80", "steps": [{"4": "N", "8": "W", "14": "W", "20": "E", "26": "S", "33": "N", "41": "W", "43": "N", "47": "E", "48": "S", "53": "N", "61": "N", "62": "N", "63": "E", "67": "W", "69": "S", "71": "W", "9": "N", "10": "W", "15": "W", "22": "N", "28": "E", "37": "W", "45": "E", "51": "S", "58": "W", "65": "E", "73": "S", "74": "S", "79": "S", "1": "S", "3": "S", "17": "N", "42": "S", "59": "W", "60": "N", "78": "S", "0": "W", "2": "E", "6": "E", "18": "W", "21": "E", "23": "N", "27": "W", "32": "E", "34": "S", "46": "S", "57": "W", "68": "W", "75": "S", "12": "W", "24": "N", "29": "S", "31": "W", "54": "N", "55": "E", "56": "E", "11": "S", "13": "E", "36": "N", "39": "E", "44": "S", "50": "N", "52": "E", "5": "W", "7": "N", "19": "N", "25": "W", "66": "S", "77": "S", "35": "W", "38": "W", "40": "W", "76": "E", "16": "N", "49": "E", "64": "W", "70": "W", "72": "W", "30": "E"}, {"4": "N", "8": "W", "14": "W", "20": "E", "26": "S", "33": "N", "41": "W", "43": "N", "47": "E", "48": "S", "53": "N", "61": "N", "62": "N", "63": "E", "67": "W", "69": "S", "71": "W", "9": "N", "10": "W", "15": "W", "22": "N", "28": "E", "37": "W", "45": "E", "51": "S", "58": "W", "65": "E", "73": "S", "74": "S", "79": "S", "1": "S", "3": "S", "17": "N", "42": "S", "59": "W", "60": "N", "78": "S", "0": "W", "2": "E", "6": "E", "18": "W", "21": "E", "23": "N", "27": "W", "32": "E", "34": "S", "46": "S", "57": "W", "68": "W", "75": "S", "12": "W", "24": "N", "29": "S", "31": "W", "54": "N", "55": "E", "56": "E", "11": "S", "13": "E", "36": "N", "39": "E", "44": "S", "50": "N", "52": "E", "5": "W", "7": "N", "19": "N", "25": "W", "66": "S", "77": "S", "35": "W", "38": "W", "40": "W", "76": "E", "16": "N", "49": "E", "64": "W", "70": "W", "72": "W", "30": "E"}, {"4": "E", "14": "N", "20": "N", "26": "W", "41": "S", "43": "W", "48": "W", "53": "W", "61": "W", "9": "N", "10": "W", "22": "N", "28": "E", "37": "W", "45": "E", "51": "S", "58": "W", "65": "E", "73": "S", "74": "S", "79": "S", "1": "S", "3": "S", "17": "N", "42": "S", "59": "W", "60": "N", "78": "S", "0": "W", "2": "E", "6": "E", "18": "W", "21": "E", "23": "N", "27": "W", "32": "E", "34": "S", "46": "S", "57": "W", "68": "W", "75": "S", "12": "W", "24": "N", "29": "S", "31": "W", "54": "N", "55": "E", "56": "E", "11": "S", "13": "E", "36": "N", "39": "E", "44": "S", "50": "N", "52": "E", "5": "W", "7": "N", "19": "N", "25": "W", "66": "S", "77": "S", "35": "W", "38": "W", "40": "W", "76": "E", "16": "N", "49": "E", "64": "W", "70": "W", "72": "W", "30": "E"}, {"14": "W", "33": "N", "48": "S", "9": "W", "10": "W", "15": "W", "22": "W", "28": "N", "37": "N", "45": "N", "51": "S", "58": "N", "73": "S", "79": "E", "1": "S", "3": "S", "17": "N", "42": "S", "59": "W", "60": "N", "78": "S", "0": "W", "2": "E", "6": "E", "18": "W", "21": "E", "23": "N", "27": "W", "32": "E", "34": "S", "46": "S", "57": "W", "68": "W", "75": "S", "12": "W", "24": "N", "29": "S", "31": "W", "54": "N", "55": "E", "56": "E", "11": "S", "13": "E", "36": "N", "39": "E", "44": "S", "50": "N", "52": "E", "5": "W", "7": "N", "19": "N", "25": "W", "66": "S", "77": "S", "35": "W", "38": "W", "40": "W", "76": "E", "16": "N", "49": "E", "64": "W", "70": "W", "72": "W", "30": "E"}, {"14": "W", "33": "N", "48": "S", "63": "E", "10": "W", "28": "E", "51": "S", "73": "S", "59": "W", "2": "E", "6": "E", "18": "W", "21": "E", "23": "N", "27": "W", "32": "E", "34": "S", "46": "S", "57": "W", "68": "W", "75": "S", "12": "W", "24": "N", "29": "S", "31": "W", "54": "N", "55": "E", "56": "E", "11": "S", "13": "E", "36": "N", "39": "E", "44": "S", "50": "N", "52": "E", "5": "W", "7": "N", "19": "N", "25": "W", "66": "S", "77": "S", "35": "W", "38": "W", "40": "W", "76": "E", "16": "N", "49": "E", "64": "W", "70": "W", "72": "W", "30": "E"}, {"63": "E", "10": "W", "28": "E", "45": "E", "65": "E", "59": "W", "2": "E", "18": "W", "21": "S", "23": "N", "27": "W", "34": "S", "46": "S", "57": "W", "68": "S", "12": "W", "24": "N", "29": "S", "54": "N", "55": "E", "56": "E", "11": "S", "13": "E", "36": "N", "39": "E", "44": "S", "50": "N", "52": "E", "5": "W", "7": "N", "19": "N", "25": "W", "66": "S", "77": "S", "35": "W", "38": "W", "40": "W", "76": "E", "16": "N", "49": "E", "64": "W", "70": "W", "72": "W", "30": "E"}, {"43": "N", "53": "N", "10": "W", "45": "E", "65": "E", "59": "W", "2": "E", "18": "N", "21": "E", "23": "N", "27": "W", "34": "S", "46": "W", "57": "N", "68": "W", "24": "N", "29": "S", "31": "W", "56": "E", "11": "S", "13": "E", "36": "N", "39": "E", "44": "S", "50": "N", "52": "E", "5": "W", "7": "N", "19": "N", "25": "W", "66": "S", "77": "S", "35": "W", "38": "W", "40": "W", "76": "E", "16": "N", "49": "E", "64": "W", "70": "W", "72": "W", "30": "E"}, {"14": "W", "43": "N", "53": "N", "71": "W", "10": "W", "45": "E", "79": "S", "17": "N", "59": "W", "2": "E", "18": "W", "21": "E", "34": "S", "46": "S", "57": "W", "68": "W", "24": "E", "29": "S", "56": "E", "11": "E", "39": "N", "44": "S", "5": "W", "7": "N", "19": "N", "25": "W", "66": "S", "77": "S", "35": "W", "38": "W", "40": "W", "76": "E", "16": "N", "49": "E", "64": "W", "70": "W", "72": "W", "30": "E"}, {"14": "W", "71": "W", "10": "W", "45": "E", "79": "S", "17": "N", "2": "S", "23": "N", "34": "S", "24": "N", "29": "W", "31": "W", "44": "W", "7": "N", "25": "S", "77": "S", "35": "W", "38": "W", "76": "E", "16": "N", "49": "E", "64": "W", "72": "W", "30": "E"}, {"2": "E", "23": "N", "32": "E", "34": "W", "68": "W", "31": "W", "36": "N", "44": "S", "5": "W", "7": "W", "25": "W", "77": "W", "35": "W", "40": "W", "16": "N", "49": "E", "64": "W", "70": "W", "72": "W", "30": "E"}, {"43": "N", "48": "S", "53": "N", "63": "E", "71": "W", "32": "E", "68": "W", "36": "N", "5": "W", "7": "N", "25": "W", "77": "S", "35": "N", "40": "W", "64": "W", "70": "W", "30": "E"}, {"43": "N", "48": "S", "53": "N", "63": "E", "71": "W", "57": "W", "25": "W", "35": "W", "40": "W", "64": "N", "30": "E"}, {"14": "W", "57": "W", "5": "W", "25": "W", "64": "W", "30": "N"}, {"14": "W", "71": "W", "5": "W", "30": "E"}, {"71": "W"}, {}], "result": "STUCK", "makespan": 15, "sum": 553, "algo_name": "OutAndInBFS_default"}