{"instance": "small_011_20x20_90_183", "steps": [{"158": "W", "127": "S", "10": "E", "77": "E", "48": "E", "178": "W", "118": "W", "59": "S", "128": "W", "43": "W", "70": "N", "65": "W", "55": "E", "6": "N", "142": "W", "174": "W", "145": "S", "16": "N", "72": "S", "27": "W", "9": "E", "175": "S", "109": "N", "1": "N", "25": "N", "179": "W", "113": "W", "141": "W", "177": "E", "22": "E", "83": "W", "37": "S", "90": "N", "138": "E", "153": "W", "180": "S", "71": "N", "87": "W", "54": "N", "160": "W", "7": "W", "114": "S", "11": "N", "144": "W", "93": "N", "120": "W", "63": "E", "168": "W", "110": "E", "151": "W", "51": "N", "81": "E", "64": "N", "176": "S", "13": "W", "24": "W", "130": "W", "171": "E", "163": "W", "94": "N", "161": "W", "57": "N", "99": "W", "106": "W", "2": "N", "26": "W", "79": "W", "102": "W", "157": "W", "129": "W", "156": "W", "69": "E", "46": "N", "104": "N", "56": "N", "76": "N", "0": "N", "167": "W", "132": "W", "108": "W", "136": "W", "159": "S", "181": "W", "97": "N", "166": "W", "14": "W", "74": "E", "95": "W", "137": "W", "103": "S", "12": "W", "147": "E", "105": "N", "133": "S", "41": "E", "91": "N", "111": "E", "62": "E", "173": "W", "149": "W", "8": "N", "89": "W", "75": "W", "146": "W", "60": "W", "61": "N", "170": "W", "154": "W", "68": "W", "50": "N", "20": "N", "5": "W", "49": "W", "35": "W", "39": "N", "15": "N", "123": "W", "169": "E", "148": "W", "31": "N", "135": "W", "140": "W", "67": "N", "38": "W", "126": "N", "101": "E", "100": "N", "162": "S", "150": "W", "165": "E", "29": "W", "112": "N", "182": "S", "172": "E", "116": "E"}, {"158": "W", "131": "E", "127": "S", "10": "E", "77": "E", "48": "E", "178": "W", "118": "W", "59": "S", "88": "S", "128": "W", "43": "W", "70": "N", "65": "W", "55": "E", "6": "N", "142": "W", "174": "W", "145": "S", "16": "N", "72": "S", "27": "W", "9": "E", "124": "W", "175": "S", "58": "E", "109": "N", "1": "N", "30": "E", "32": "W", "25": "N", "179": "W", "113": "W", "141": "W", "80": "E", "177": "E", "83": "W", "85": "E", "37": "S", "90": "N", "138": "S", "153": "W", "180": "S", "71": "N", "87": "W", "164": "W", "160": "W", "7": "W", "114": "S", "78": "S", "34": "W", "11": "N", "144": "W", "93": "E", "120": "W", "66": "W", "168": "W", "28": "S", "110": "E", "151": "W", "51": "N", "44": "S", "81": "N", "64": "W", "176": "S", "13": "W", "24": "W", "130": "W", "171": "E", "40": "E", "17": "S", "163": "W", "161": "W", "57": "N", "99": "W", "106": "W", "82": "E", "26": "W", "79": "W", "102": "W", "157": "W", "129": "W", "156": "W", "69": "N", "96": "S", "46": "W", "122": "S", "104": "N", "56": "N", "76": "N", "167": "W", "132": "W", "73": "W", "107": "E", "21": "S", "117": "W", "119": "E", "108": "W", "136": "W", "159": "S", "181": "W", "97": "N", "166": "W", "95": "W", "137": "S", "103": "E", "12": "W", "147": "N", "133": "S", "4": "E", "41": "E", "111": "S", "62": "E", "173": "W", "149": "W", "89": "W", "75": "W", "146": "W", "115": "S", "60": "W", "61": "N", "170": "W", "154": "W", "68": "W", "139": "E", "50": "N", "5": "W", "33": "S", "49": "W", "35": "W", "15": "N", "123": "W", "169": "S", "148": "W", "31": "N", "135": "W", "140": "W", "67": "N", "42": "E", "38": "W", "101": "E", "162": "W", "150": "W", "165": "E", "29": "W", "112": "N", "182": "S", "3": "E", "172": "E", "23": "E", "116": "N"}, {"158": "W", "131": "E", "127": "S", "10": "E", "77": "E", "48": "E", "178": "W", "118": "W", "59": "E", "88": "W", "128": "W", "43": "W", "70": "N", "65": "W", "55": "E", "6": "N", "142": "W", "174": "W", "145": "S", "16": "N", "72": "S", "155": "W", "27": "W", "9": "E", "124": "N", "175": "S", "109": "N", "1": "N", "30": "E", "32": "S", "25": "N", "179": "W", "45": "W", "113": "W", "80": "E", "177": "E", "22": "W", "83": "W", "85": "E", "37": "S", "90": "N", "138": "W", "153": "W", "71": "N", "87": "W", "54": "W", "164": "W", "160": "W", "114": "S", "78": "W", "34": "W", "11": "N", "144": "W", "93": "S", "66": "N", "63": "W", "110": "E", "151": "W", "86": "W", "51": "N", "44": "S", "81": "W", "64": "W", "98": "S", "13": "W", "24": "W", "130": "W", "171": "E", "40": "E", "17": "S", "161": "W", "57": "N", "99": "W", "106": "W", "26": "W", "79": "N", "102": "W", "157": "W", "129": "W", "156": "W", "69": "N", "46": "S", "122": "E", "19": "S", "104": "N", "56": "N", "76": "N", "0": "E", "107": "N", "21": "E", "119": "S", "136": "W", "159": "S", "181": "S", "97": "N", "166": "W", "95": "W", "137": "W", "103": "E", "12": "W", "147": "E", "152": "E", "133": "E", "4": "E", "41": "E", "111": "E", "149": "W", "8": "W", "75": "S", "146": "W", "115": "S", "61": "N", "52": "E", "68": "W", "139": "E", "50": "N", "5": "W", "49": "W", "35": "W", "169": "E", "148": "W", "31": "N", "135": "W", "140": "W", "67": "N", "42": "N", "38": "W", "100": "N", "162": "W", "150": "S", "165": "E", "29": "W", "112": "N", "3": "N", "53": "E"}, {"158": "W", "131": "S", "127": "S", "77": "N", "48": "E", "178": "W", "118": "W", "59": "N", "128": "W", "43": "W", "70": "N", "65": "W", "6": "N", "142": "W", "174": "W", "145": "W", "72": "S", "9": "E", "124": "W", "175": "S", "109": "N", "30": "E", "32": "W", "25": "W", "179": "W", "45": "W", "113": "W", "141": "W", "177": "N", "83": "W", "37": "S", "90": "N", "153": "W", "71": "N", "87": "W", "54": "W", "160": "W", "7": "S", "114": "S", "78": "W", "34": "W", "11": "N", "144": "W", "93": "S", "66": "N", "168": "W", "28": "N", "110": "E", "151": "W", "86": "W", "51": "N", "44": "S", "81": "N", "64": "W", "176": "S", "98": "S", "13": "W", "24": "W", "171": "S", "40": "E", "17": "S", "163": "W", "161": "W", "57": "N", "99": "W", "106": "W", "82": "E", "79": "E", "121": "N", "102": "W", "157": "W", "129": "W", "156": "W", "69": "W", "46": "W", "122": "E", "56": "N", "76": "N", "0": "E", "167": "W", "73": "E", "92": "N", "107": "N", "117": "E", "119": "E", "108": "S", "136": "W", "159": "S", "181": "W", "97": "N", "166": "W", "74": "W", "137": "W", "152": "E", "105": "N", "133": "E", "91": "E", "111": "S", "173": "W", "149": "W", "8": "N", "75": "W", "146": "W", "115": "E", "61": "N", "170": "W", "52": "E", "154": "W", "68": "S", "50": "N", "5": "W", "33": "S", "49": "W", "35": "W", "169": "E", "148": "W", "31": "N", "135": "W", "47": "E", "140": "W", "67": "N", "42": "N", "38": "W", "101": "E", "100": "N", "162": "W", "150": "S", "165": "N", "29": "W", "112": "N", "182": "W", "3": "N", "172": "E", "23": "W", "116": "N"}, {"158": "W", "131": "S", "127": "S", "10": "E", "48": "E", "178": "W", "118": "W", "128": "W", "43": "W", "70": "N", "65": "S", "55": "E", "142": "W", "174": "W", "145": "W", "72": "S", "9": "E", "109": "N", "30": "S", "32": "W", "179": "W", "45": "W", "113": "W", "80": "E", "177": "N", "83": "W", "37": "S", "90": "N", "153": "W", "134": "N", "71": "N", "87": "W", "54": "W", "160": "W", "78": "W", "34": "W", "11": "N", "144": "W", "120": "N", "63": "N", "168": "W", "28": "E", "110": "E", "151": "W", "86": "W", "51": "E", "44": "S", "81": "N", "64": "S", "176": "S", "98": "S", "13": "S", "24": "W", "171": "W", "17": "S", "163": "W", "94": "N", "161": "W", "106": "W", "82": "E", "2": "S", "79": "S", "121": "N", "102": "W", "157": "W", "129": "W", "156": "W", "69": "N", "46": "W", "122": "N", "104": "N", "56": "N", "76": "N", "0": "E", "167": "W", "73": "E", "92": "N", "107": "W", "117": "S", "119": "E", "108": "S", "136": "W", "159": "S", "181": "W", "97": "N", "166": "W", "14": "S", "74": "W", "95": "N", "137": "S", "103": "S", "152": "E", "105": "N", "133": "E", "41": "N", "91": "N", "111": "E", "62": "S", "173": "S", "149": "W", "8": "N", "89": "S", "75": "W", "146": "W", "170": "S", "52": "E", "154": "W", "50": "N", "5": "W", "49": "W", "35": "W", "39": "S", "15": "N", "169": "E", "148": "W", "31": "N", "135": "W", "140": "W", "67": "N", "42": "N", "38": "N", "101": "S", "100": "N", "162": "S", "150": "S", "29": "W", "112": "N", "3": "W", "116": "N"}, {"158": "W", "131": "E", "127": "W", "10": "E", "59": "W", "128": "W", "43": "W", "70": "N", "142": "W", "174": "W", "145": "N", "72": "S", "9": "S", "109": "N", "30": "E", "32": "W", "179": "W", "45": "W", "113": "W", "177": "W", "85": "N", "37": "S", "138": "E", "153": "W", "134": "E", "71": "N", "87": "W", "54": "W", "164": "S", "7": "S", "114": "E", "78": "W", "34": "W", "144": "W", "120": "N", "63": "W", "168": "W", "28": "S", "110": "S", "151": "W", "86": "N", "51": "E", "44": "S", "81": "N", "64": "W", "176": "E", "98": "S", "13": "E", "24": "W", "171": "W", "17": "S", "163": "W", "94": "N", "161": "W", "106": "W", "82": "N", "2": "S", "26": "W", "79": "S", "121": "N", "102": "W", "157": "W", "129": "W", "156": "W", "69": "N", "46": "S", "122": "N", "19": "S", "104": "N", "56": "N", "0": "E", "167": "W", "132": "N", "92": "N", "107": "N", "21": "E", "117": "W", "119": "E", "108": "S", "136": "W", "159": "S", "18": "E", "181": "W", "97": "W", "166": "W", "14": "W", "74": "N", "137": "W", "103": "S", "12": "E", "147": "S", "152": "E", "105": "N", "133": "S", "91": "E", "111": "S", "62": "E", "173": "S", "149": "W", "8": "N", "89": "S", "75": "W", "146": "W", "115": "E", "60": "S", "61": "E", "170": "S", "52": "E", "154": "W", "68": "W", "50": "E", "20": "N", "5": "N", "49": "W", "39": "W", "15": "E", "123": "S", "169": "E", "148": "W", "135": "W", "140": "W", "42": "N", "38": "E", "126": "N", "101": "S", "100": "E", "162": "S", "150": "S", "29": "W", "182": "E", "3": "N", "172": "E", "53": "S", "116": "E"}, {"158": "W", "131": "E", "127": "W", "10": "N", "59": "W", "128": "W", "43": "W", "70": "E", "55": "W", "174": "W", "145": "N", "16": "E", "9": "S", "30": "N", "32": "W", "179": "W", "45": "W", "177": "N", "22": "N", "85": "E", "138": "S", "153": "W", "134": "S", "87": "S", "54": "W", "164": "W", "7": "S", "114": "N", "78": "S", "120": "N", "66": "N", "63": "N", "28": "S", "110": "S", "151": "W", "51": "E", "44": "E", "81": "W", "64": "W", "176": "N", "98": "S", "13": "E", "171": "N", "17": "S", "163": "W", "94": "N", "161": "W", "106": "N", "82": "E", "26": "S", "79": "S", "121": "N", "157": "W", "129": "W", "156": "W", "69": "W", "96": "W", "46": "W", "122": "E", "19": "S", "104": "W", "56": "W", "76": "N", "36": "E", "167": "W", "132": "E", "92": "N", "107": "N", "117": "S", "119": "E", "108": "S", "136": "W", "159": "W", "18": "S", "97": "W", "166": "W", "14": "S", "137": "S", "103": "S", "12": "E", "152": "E", "105": "N", "133": "E", "4": "W", "91": "E", "111": "E", "173": "S", "149": "W", "8": "N", "89": "S", "75": "S", "146": "W", "115": "S", "60": "S", "61": "S", "170": "S", "52": "E", "154": "W", "68": "S", "139": "S", "50": "N", "20": "E", "5": "N", "49": "N", "35": "E", "39": "W", "123": "S", "169": "E", "148": "W", "135": "W", "140": "W", "42": "N", "38": "E", "126": "N", "101": "W", "100": "E", "143": "W", "162": "W", "150": "S", "165": "N", "29": "N", "112": "W", "182": "N", "3": "N", "172": "N", "53": "S", "116": "N"}, {"158": "W", "131": "E", "127": "W", "10": "N", "48": "N", "59": "W", "128": "N", "43": "W", "70": "S", "55": "W", "174": "W", "145": "W", "16": "S", "9": "W", "30": "N", "32": "W", "179": "S", "45": "W", "177": "N", "22": "W", "85": "E", "138": "E", "134": "W", "87": "S", "54": "W", "7": "S", "114": "N", "34": "W", "120": "N", "63": "W", "28": "S", "110": "W", "151": "N", "51": "S", "44": "S", "81": "N", "64": "W", "176": "E", "13": "E", "24": "W", "163": "W", "94": "N", "161": "S", "57": "E", "106": "N", "82": "E", "26": "S", "79": "S", "121": "W", "157": "W", "129": "W", "156": "W", "69": "W", "96": "S", "46": "S", "122": "E", "19": "E", "56": "W", "76": "N", "36": "N", "167": "W", "132": "N", "92": "E", "107": "N", "21": "E", "117": "S", "119": "S", "159": "W", "18": "E", "97": "W", "166": "W", "14": "S", "74": "N", "137": "W", "103": "E", "12": "N", "152": "E", "105": "N", "133": "E", "4": "S", "91": "S", "125": "W", "111": "N", "173": "S", "149": "W", "8": "N", "89": "S", "75": "S", "146": "W", "60": "E", "61": "E", "52": "E", "154": "W", "68": "S", "139": "E", "50": "N", "20": "E", "5": "N", "49": "N", "35": "N", "39": "W", "123": "S", "169": "S", "148": "W", "135": "W", "140": "W", "42": "N", "101": "S", "100": "E", "143": "W", "150": "E", "165": "N", "112": "N", "182": "W", "3": "N", "172": "E", "53": "W", "116": "N"}, {"131": "E", "127": "W", "10": "W", "77": "S", "48": "W", "59": "W", "128": "W", "43": "W", "70": "E", "55": "W", "16": "S", "9": "W", "109": "E", "30": "N", "32": "W", "179": "S", "45": "S", "113": "N", "177": "N", "22": "W", "85": "E", "84": "E", "138": "E", "153": "W", "134": "S", "87": "S", "54": "S", "7": "S", "114": "N", "120": "N", "66": "N", "63": "N", "151": "E", "86": "S", "51": "S", "44": "S", "81": "W", "64": "S", "176": "N", "13": "E", "24": "W", "40": "N", "94": "W", "161": "S", "57": "S", "106": "N", "82": "E", "2": "N", "26": "S", "79": "S", "121": "N", "102": "N", "69": "W", "96": "S", "46": "S", "122": "E", "56": "W", "36": "N", "132": "N", "92": "E", "107": "N", "117": "W", "119": "S", "136": "W", "159": "W", "18": "E", "97": "W", "14": "S", "74": "W", "95": "S", "137": "W", "103": "E", "12": "E", "105": "N", "133": "N", "41": "E", "91": "E", "125": "W", "111": "E", "173": "S", "8": "N", "89": "S", "75": "S", "61": "S", "154": "S", "68": "S", "50": "N", "20": "E", "5": "E", "49": "N", "35": "N", "39": "N", "15": "S", "123": "S", "169": "E", "31": "E", "47": "W", "42": "W", "126": "N", "101": "S", "100": "E", "143": "W", "162": "S", "150": "E", "165": "N", "29": "S", "112": "W", "182": "N", "3": "N", "172": "N", "53": "S", "23": "N", "116": "N"}, {"131": "E", "127": "S", "10": "N", "77": "W", "48": "W", "118": "N", "59": "W", "128": "N", "43": "S", "70": "S", "55": "W", "174": "N", "16": "S", "72": "W", "155": "S", "9": "W", "175": "W", "109": "N", "30": "E", "179": "S", "45": "S", "113": "E", "177": "N", "22": "W", "85": "E", "84": "E", "138": "E", "153": "W", "87": "S", "54": "S", "7": "S", "114": "N", "11": "W", "120": "E", "66": "W", "63": "N", "86": "W", "51": "S", "44": "S", "81": "W", "64": "S", "176": "E", "24": "N", "40": "N", "163": "W", "94": "N", "57": "S", "106": "E", "82": "E", "2": "E", "26": "S", "79": "S", "121": "N", "102": "E", "69": "N", "96": "S", "46": "S", "56": "W", "76": "N", "0": "W", "36": "W", "167": "W", "132": "N", "107": "W", "117": "S", "119": "S", "108": "S", "136": "W", "159": "W", "18": "E", "97": "W", "14": "S", "74": "W", "95": "S", "137": "W", "147": "W", "152": "E", "133": "N", "4": "S", "125": "N", "111": "S", "62": "E", "149": "N", "89": "S", "75": "S", "61": "S", "52": "E", "68": "S", "139": "E", "50": "E", "5": "E", "35": "E", "15": "W", "123": "S", "169": "S", "31": "E", "47": "S", "42": "N", "38": "S", "100": "S", "143": "W", "150": "E", "165": "N", "112": "W", "3": "W", "172": "W"}, {"131": "E", "127": "W", "10": "W", "77": "W", "48": "W", "118": "E", "59": "W", "128": "N", "43": "S", "70": "S", "55": "W", "145": "W", "16": "E", "72": "N", "155": "S", "9": "W", "109": "E", "30": "N", "32": "N", "179": "S", "45": "S", "113": "E", "22": "N", "85": "E", "37": "W", "84": "E", "138": "E", "153": "W", "134": "S", "87": "E", "54": "S", "7": "S", "114": "E", "34": "N", "11": "S", "120": "E", "66": "W", "63": "N", "110": "S", "86": "S", "44": "S", "64": "S", "176": "E", "24": "N", "40": "N", "163": "W", "94": "N", "57": "S", "106": "E", "82": "N", "26": "E", "79": "S", "121": "N", "102": "E", "69": "N", "96": "S", "46": "S", "19": "S", "56": "W", "76": "N", "0": "N", "167": "W", "132": "N", "92": "S", "107": "W", "21": "E", "119": "S", "108": "S", "136": "N", "159": "W", "18": "E", "97": "W", "14": "S", "74": "W", "137": "W", "103": "E", "147": "S", "105": "N", "133": "E", "4": "E", "125": "W", "111": "E", "62": "E", "149": "E", "8": "N", "115": "W", "60": "S", "61": "E", "170": "E", "68": "S", "139": "N", "50": "N", "20": "S", "5": "E", "33": "S", "35": "E", "15": "S", "123": "S", "148": "N", "31": "S", "47": "S", "67": "E", "42": "N", "100": "E", "143": "S", "150": "S", "165": "N", "112": "W", "172": "N", "23": "S"}, {"131": "E", "127": "W", "10": "W", "77": "W", "48": "W", "178": "S", "118": "E", "59": "W", "128": "N", "43": "S", "70": "S", "65": "S", "55": "W", "145": "W", "16": "E", "72": "N", "155": "S", "9": "W", "175": "W", "109": "E", "30": "N", "32": "N", "45": "S", "113": "N", "22": "N", "85": "S", "37": "N", "84": "N", "138": "E", "153": "S", "134": "S", "87": "S", "54": "S", "160": "S", "7": "S", "114": "E", "120": "E", "66": "W", "63": "N", "110": "W", "86": "W", "51": "S", "44": "S", "64": "S", "176": "E", "13": "S", "24": "N", "40": "E", "163": "W", "94": "W", "57": "E", "99": "S", "106": "E", "82": "E", "2": "S", "79": "S", "121": "E", "102": "E", "69": "N", "46": "S", "122": "S", "19": "E", "104": "E", "56": "W", "76": "W", "167": "W", "132": "N", "92": "E", "107": "N", "21": "E", "119": "W", "108": "S", "136": "N", "159": "W", "18": "E", "181": "S", "97": "W", "14": "S", "137": "S", "103": "E", "147": "S", "105": "N", "133": "E", "41": "S", "125": "W", "111": "E", "62": "N", "149": "N", "8": "W", "89": "S", "60": "S", "68": "S", "139": "N", "50": "E", "20": "E", "5": "E", "33": "S", "35": "E", "39": "W", "15": "E", "123": "S", "31": "S", "47": "S", "67": "E", "42": "W", "101": "S", "100": "E", "143": "S", "112": "W", "172": "N", "53": "E"}, {"131": "E", "127": "W", "10": "W", "77": "W", "48": "W", "178": "E", "118": "E", "59": "W", "128": "E", "43": "S", "70": "S", "65": "S", "55": "W", "6": "E", "142": "S", "145": "W", "16": "E", "72": "N", "155": "S", "9": "W", "175": "N", "58": "N", "109": "E", "30": "E", "32": "W", "179": "S", "45": "S", "113": "N", "177": "N", "22": "N", "85": "E", "37": "W", "84": "E", "138": "E", "153": "S", "134": "W", "87": "S", "54": "S", "160": "E", "7": "S", "114": "E", "78": "N", "34": "E", "120": "E", "66": "W", "63": "N", "110": "W", "86": "S", "51": "S", "44": "W", "81": "S", "64": "S", "13": "S", "24": "E", "171": "W", "40": "N", "163": "N", "94": "N", "161": "S", "99": "S", "106": "E", "82": "N", "2": "E", "79": "E", "121": "E", "102": "E", "69": "N", "46": "S", "122": "E", "19": "E", "104": "S", "56": "S", "76": "W", "167": "S", "132": "E", "73": "N", "92": "N", "107": "N", "21": "E", "119": "W", "136": "N", "159": "W", "18": "E", "181": "E", "97": "W", "14": "S", "74": "W", "95": "S", "137": "W", "103": "E", "12": "S", "105": "W", "133": "E", "4": "E", "41": "E", "91": "N", "125": "S", "111": "E", "149": "E", "8": "N", "89": "S", "60": "S", "154": "E", "68": "S", "139": "N", "50": "S", "20": "N", "5": "E", "49": "N", "35": "E", "39": "W", "15": "S", "123": "S", "169": "W", "31": "S", "47": "W", "67": "S", "42": "N", "126": "S", "101": "S", "100": "S", "143": "S", "162": "S", "165": "N", "112": "W", "182": "S", "3": "E", "172": "N", "53": "S", "23": "E"}, {"131": "E", "127": "N", "10": "S", "77": "W", "48": "W", "178": "E", "118": "S", "59": "W", "128": "E", "43": "S", "70": "S", "65": "E", "55": "W", "6": "S", "142": "E", "145": "N", "16": "S", "72": "N", "155": "S", "9": "W", "175": "N", "58": "E", "109": "E", "30": "E", "32": "W", "179": "E", "45": "S", "113": "E", "80": "S", "177": "N", "22": "W", "85": "E", "37": "W", "84": "E", "90": "E", "138": "E", "153": "S", "180": "S", "134": "S", "87": "E", "54": "S", "160": "E", "7": "S", "114": "N", "78": "E", "144": "N", "120": "E", "66": "W", "168": "N", "110": "W", "151": "S", "86": "W", "51": "E", "44": "S", "81": "W", "64": "S", "13": "S", "24": "E", "94": "W", "161": "E", "99": "E", "106": "E", "82": "N", "79": "E", "121": "N", "102": "N", "46": "S", "122": "N", "19": "S", "104": "E", "56": "W", "76": "W", "132": "E", "73": "N", "107": "W", "21": "N", "119": "S", "136": "N", "159": "W", "18": "E", "97": "S", "14": "E", "74": "W", "137": "S", "103": "E", "152": "E", "105": "N", "133": "E", "91": "N", "125": "S", "111": "S", "149": "N", "8": "W", "89": "E", "60": "S", "170": "N", "52": "E", "154": "N", "68": "S", "139": "N", "50": "S", "20": "N", "49": "N", "35": "N", "123": "S", "169": "N", "148": "S", "31": "E", "47": "S", "67": "S", "42": "W", "38": "S", "100": "S", "143": "W", "162": "S", "165": "N", "29": "N", "112": "W", "3": "N", "172": "N", "53": "W"}, {"131": "E", "127": "W", "10": "S", "77": "W", "48": "W", "178": "E", "118": "E", "59": "W", "128": "E", "43": "S", "70": "E", "65": "E", "55": "W", "6": "S", "142": "E", "145": "W", "16": "S", "72": "N", "155": "W", "9": "W", "175": "W", "58": "E", "109": "E", "30": "E", "32": "W", "179": "E", "113": "E", "80": "S", "177": "N", "22": "W", "85": "E", "37": "W", "84": "N", "90": "S", "138": "E", "153": "S", "134": "W", "87": "E", "54": "S", "160": "E", "114": "N", "34": "N", "144": "E", "120": "E", "66": "W", "168": "E", "110": "W", "151": "E", "86": "W", "44": "W", "81": "W", "64": "S", "13": "S", "24": "E", "171": "W", "94": "W", "161": "E", "99": "E", "106": "E", "82": "E", "121": "N", "102": "N", "69": "N", "46": "S", "122": "N", "104": "E", "56": "W", "76": "W", "73": "E", "107": "N", "21": "N", "119": "W", "136": "N", "159": "W", "18": "E", "181": "S", "74": "N", "137": "W", "103": "E", "12": "S", "105": "W", "133": "E", "91": "E", "125": "S", "111": "E", "62": "N", "8": "W", "89": "S", "115": "E", "60": "E", "61": "N", "52": "N", "68": "E", "139": "N", "50": "S", "33": "N", "49": "E", "39": "W", "169": "E", "148": "E", "31": "S", "47": "S", "140": "E", "42": "W", "38": "S", "100": "E", "162": "S", "165": "N", "112": "N", "182": "S", "172": "N"}, {"131": "N", "127": "W", "10": "S", "77": "S", "48": "W", "178": "E", "118": "E", "59": "W", "128": "E", "43": "S", "70": "E", "65": "E", "55": "N", "6": "S", "142": "E", "145": "W", "16": "S", "72": "N", "155": "W", "9": "S", "175": "W", "58": "S", "109": "N", "30": "E", "32": "W", "179": "N", "113": "E", "80": "S", "177": "N", "22": "W", "85": "E", "37": "W", "84": "N", "90": "S", "138": "E", "153": "S", "134": "S", "87": "E", "54": "W", "164": "S", "160": "E", "114": "N", "34": "N", "11": "S", "144": "E", "120": "E", "66": "W", "63": "N", "168": "E", "110": "W", "151": "E", "86": "W", "51": "N", "44": "S", "81": "N", "64": "S", "13": "S", "24": "E", "94": "W", "161": "S", "99": "E", "106": "E", "82": "E", "121": "E", "102": "N", "157": "S", "69": "N", "96": "W", "46": "S", "122": "N", "104": "S", "56": "W", "76": "N", "73": "E", "107": "N", "21": "N", "119": "W", "136": "N", "159": "W", "18": "E", "181": "E", "97": "E", "74": "N", "95": "W", "137": "W", "103": "E", "147": "S", "152": "E", "105": "N", "133": "N", "41": "E", "91": "E", "125": "S", "111": "E", "8": "W", "89": "S", "146": "S", "60": "E", "61": "E", "170": "E", "52": "N", "68": "E", "139": "N", "50": "S", "49": "E", "35": "N", "31": "E", "47": "E", "67": "E", "42": "W", "38": "W", "101": "N", "100": "S", "143": "W", "162": "S", "150": "S", "165": "N", "182": "W", "172": "N", "116": "N"}, {"158": "S", "131": "N", "127": "W", "10": "W", "48": "W", "178": "N", "118": "E", "59": "W", "128": "N", "43": "S", "70": "E", "65": "E", "6": "W", "142": "E", "16": "E", "72": "E", "155": "W", "9": "W", "124": "E", "175": "W", "58": "S", "109": "E", "30": "E", "32": "W", "113": "E", "80": "E", "177": "N", "22": "W", "83": "S", "85": "S", "37": "W", "84": "N", "90": "W", "138": "E", "153": "S", "134": "W", "87": "E", "54": "W", "160": "S", "114": "N", "34": "W", "11": "W", "120": "E", "66": "W", "63": "N", "168": "E", "28": "N", "110": "W", "151": "E", "86": "W", "51": "E", "44": "W", "64": "S", "13": "E", "24": "E", "130": "S", "171": "E", "40": "N", "94": "W", "161": "E", "99": "S", "106": "E", "82": "N", "121": "E", "102": "E", "157": "S", "156": "S", "69": "N", "96": "W", "46": "S", "122": "N", "19": "S", "104": "E", "56": "S", "76": "W", "36": "E", "132": "N", "73": "E", "92": "S", "107": "N", "119": "W", "108": "S", "136": "E", "159": "W", "18": "E", "181": "E", "97": "S", "14": "S", "74": "N", "95": "N", "137": "W", "103": "N", "147": "S", "152": "N", "105": "W", "133": "N", "4": "W", "41": "E", "125": "S", "111": "E", "8": "W", "89": "E", "75": "W", "60": "E", "61": "E", "52": "W", "154": "S", "139": "N", "50": "S", "49": "E", "35": "E", "169": "W", "148": "N", "31": "S", "47": "S", "42": "W", "101": "N", "100": "E", "143": "S", "165": "N", "29": "N", "182": "S", "172": "N", "116": "N"}, {"158": "E", "131": "N", "127": "N", "10": "W", "77": "E", "48": "W", "178": "N", "118": "S", "59": "W", "128": "E", "43": "E", "70": "E", "65": "E", "6": "W", "142": "S", "174": "N", "145": "W", "16": "E", "72": "N", "155": "W", "9": "W", "175": "N", "58": "S", "109": "E", "30": "N", "32": "W", "113": "E", "177": "W", "22": "W", "83": "E", "85": "E", "37": "W", "84": "N", "90": "W", "138": "E", "153": "S", "180": "W", "71": "N", "87": "E", "54": "S", "164": "S", "160": "S", "7": "W", "114": "N", "78": "N", "34": "W", "11": "W", "144": "E", "93": "W", "66": "W", "63": "N", "168": "E", "110": "W", "151": "E", "86": "W", "51": "E", "44": "S", "64": "S", "13": "S", "24": "E", "171": "E", "40": "E", "163": "N", "94": "W", "161": "E", "57": "W", "99": "E", "82": "N", "121": "E", "102": "E", "157": "S", "156": "E", "69": "W", "46": "S", "122": "N", "104": "E", "56": "W", "76": "W", "167": "N", "132": "N", "73": "E", "92": "E", "107": "W", "21": "N", "119": "W", "136": "E", "159": "W", "18": "E", "181": "E", "97": "S", "74": "W", "95": "N", "137": "W", "103": "E", "12": "N", "147": "E", "152": "N", "105": "W", "133": "N", "41": "E", "125": "S", "111": "E", "173": "W", "8": "W", "89": "S", "60": "E", "170": "S", "52": "N", "68": "S", "139": "N", "50": "S", "5": "W", "35": "N", "39": "W", "15": "N", "123": "S", "148": "N", "31": "E", "42": "W", "38": "E", "100": "S", "150": "N", "165": "W", "112": "W", "182": "W", "3": "W", "172": "N", "53": "E", "23": "N", "116": "N"}, {"158": "E", "131": "N", "127": "N", "10": "W", "48": "W", "178": "N", "118": "S", "59": "N", "88": "E", "128": "E", "43": "E", "70": "E", "65": "E", "6": "W", "142": "E", "174": "E", "145": "W", "16": "E", "72": "N", "155": "W", "9": "W", "175": "W", "58": "E", "109": "S", "30": "N", "32": "W", "113": "N", "80": "S", "177": "N", "22": "W", "83": "E", "37": "W", "84": "N", "90": "W", "138": "E", "153": "S", "180": "W", "71": "E", "87": "S", "54": "S", "164": "W", "160": "S", "7": "N", "114": "N", "78": "N", "34": "W", "11": "W", "144": "N", "66": "W", "63": "N", "168": "E", "28": "N", "110": "S", "151": "E", "86": "W", "51": "S", "44": "W", "13": "E", "24": "E", "130": "N", "40": "N", "17": "N", "94": "W", "161": "E", "57": "W", "99": "E", "82": "N", "121": "E", "102": "N", "157": "S", "156": "E", "69": "W", "122": "N", "19": "S", "104": "E", "56": "W", "76": "W", "167": "E", "132": "E", "73": "E", "92": "N", "107": "N", "21": "N", "119": "W", "136": "E", "159": "W", "18": "E", "181": "E", "74": "N", "95": "N", "137": "S", "103": "N", "12": "W", "147": "N", "152": "N", "105": "W", "133": "N", "4": "E", "41": "N", "111": "E", "8": "W", "89": "E", "60": "E", "170": "W", "52": "W", "139": "N", "50": "S", "35": "N", "39": "S", "123": "S", "169": "E", "148": "N", "31": "E", "135": "W", "47": "S", "67": "E", "42": "W", "38": "E", "126": "W", "100": "S", "143": "W", "165": "N", "112": "W", "182": "S", "3": "W", "172": "N", "53": "E", "23": "W", "116": "N"}, {"158": "E", "131": "N", "127": "N", "10": "W", "48": "W", "178": "N", "118": "S", "59": "W", "88": "E", "128": "E", "43": "E", "70": "E", "65": "S", "6": "W", "142": "S", "174": "E", "145": "N", "16": "E", "72": "E", "155": "W", "9": "S", "124": "W", "175": "W", "58": "E", "109": "S", "30": "N", "32": "W", "113": "E", "80": "E", "177": "W", "22": "W", "83": "E", "85": "W", "37": "W", "84": "N", "90": "W", "138": "N", "153": "S", "71": "E", "87": "S", "54": "S", "164": "W", "160": "E", "7": "E", "114": "N", "78": "N", "34": "W", "11": "W", "93": "E", "66": "S", "63": "W", "168": "N", "110": "W", "151": "E", "86": "W", "51": "E", "81": "S", "64": "W", "13": "E", "24": "E", "40": "N", "17": "N", "163": "N", "94": "W", "57": "N", "82": "E", "2": "S", "121": "E", "157": "S", "156": "S", "69": "W", "96": "S", "122": "N", "19": "E", "104": "S", "56": "W", "76": "W", "167": "N", "132": "E", "92": "E", "107": "N", "21": "E", "119": "S", "108": "N", "136": "E", "159": "W", "18": "N", "97": "N", "74": "W", "95": "N", "137": "W", "103": "N", "12": "N", "147": "E", "152": "N", "105": "W", "133": "N", "4": "E", "41": "N", "111": "E", "8": "W", "89": "E", "146": "S", "60": "E", "154": "N", "139": "N", "50": "E", "20": "N", "35": "E", "39": "W", "15": "N", "123": "W", "169": "E", "148": "E", "31": "S", "135": "W", "47": "S", "67": "S", "42": "W", "38": "S", "126": "W", "100": "S", "143": "S", "162": "S", "150": "S", "165": "N", "112": "S", "182": "S", "3": "W", "172": "N", "53": "S", "116": "N"}, {"158": "E", "127": "N", "10": "W", "77": "W", "48": "N", "178": "N", "118": "E", "59": "W", "88": "E", "128": "E", "43": "E", "70": "E", "65": "E", "6": "W", "142": "S", "174": "N", "145": "W", "72": "N", "155": "W", "9": "W", "175": "W", "58": "E", "109": "S", "30": "N", "32": "S", "113": "E", "80": "S", "177": "W", "22": "W", "83": "E", "85": "W", "37": "W", "84": "N", "90": "W", "138": "N", "153": "E", "71": "E", "87": "E", "54": "S", "164": "N", "114": "N", "78": "W", "34": "W", "11": "W", "93": "E", "66": "S", "63": "W", "168": "E", "110": "W", "151": "E", "86": "S", "51": "E", "81": "W", "13": "E", "24": "N", "40": "N", "17": "W", "163": "N", "94": "W", "57": "E", "82": "E", "2": "W", "26": "E", "121": "E", "102": "N", "157": "S", "156": "S", "69": "W", "122": "N", "19": "E", "104": "S", "56": "S", "76": "W", "0": "W", "167": "E", "132": "E", "73": "S", "92": "N", "107": "N", "21": "N", "119": "S", "136": "E", "159": "W", "18": "N", "166": "W", "14": "W", "74": "W", "137": "W", "103": "E", "12": "N", "147": "E", "152": "N", "105": "W", "133": "N", "4": "E", "41": "W", "91": "W", "111": "E", "173": "S", "8": "W", "89": "E", "75": "S", "146": "S", "60": "E", "61": "N", "68": "N", "139": "N", "50": "E", "20": "W", "33": "E", "35": "N", "39": "W", "123": "N", "169": "N", "135": "W", "47": "E", "140": "W", "67": "E", "42": "W", "38": "S", "126": "W", "101": "E", "100": "E", "143": "S", "162": "E", "165": "W", "112": "W", "182": "W", "3": "W", "172": "W", "116": "N"}, {"158": "N", "127": "N", "48": "N", "178": "E", "118": "S", "59": "W", "88": "E", "128": "E", "43": "E", "70": "S", "65": "E", "55": "N", "6": "W", "142": "S", "174": "E", "145": "N", "16": "E", "72": "E", "155": "W", "9": "W", "175": "W", "109": "S", "30": "N", "32": "S", "113": "E", "80": "E", "177": "W", "22": "W", "83": "E", "37": "W", "84": "N", "90": "W", "138": "E", "153": "E", "134": "E", "71": "E", "87": "E", "54": "S", "164": "N", "114": "N", "78": "W", "34": "W", "11": "W", "93": "E", "66": "S", "63": "W", "110": "W", "86": "W", "51": "E", "44": "W", "81": "W", "13": "E", "40": "E", "17": "W", "163": "N", "94": "W", "57": "N", "106": "S", "82": "E", "2": "S", "79": "S", "121": "E", "102": "N", "156": "S", "69": "W", "46": "W", "122": "N", "19": "N", "104": "E", "76": "W", "36": "W", "167": "E", "132": "E", "92": "N", "107": "N", "21": "N", "119": "W", "136": "E", "159": "N", "18": "N", "166": "N", "14": "N", "74": "W", "95": "N", "137": "W", "103": "N", "12": "W", "147": "N", "152": "N", "105": "W", "133": "N", "4": "E", "41": "N", "91": "N", "125": "W", "111": "N", "173": "S", "8": "W", "89": "E", "75": "S", "146": "S", "60": "E", "61": "N", "52": "E", "154": "E", "50": "E", "5": "N", "35": "E", "39": "S", "15": "N", "135": "S", "47": "E", "140": "S", "67": "E", "42": "W", "38": "S", "100": "S", "143": "S", "162": "E", "165": "N", "29": "N", "112": "W", "3": "W", "172": "N", "23": "N", "116": "N"}, {"158": "E", "127": "N", "48": "W", "178": "E", "118": "S", "59": "N", "88": "S", "128": "E", "43": "E", "70": "S", "65": "N", "6": "W", "142": "S", "145": "N", "16": "E", "72": "E", "9": "W", "175": "W", "109": "S", "30": "N", "32": "S", "113": "E", "80": "E", "177": "W", "22": "W", "83": "E", "37": "W", "84": "N", "90": "W", "138": "N", "153": "S", "71": "S", "87": "E", "54": "S", "164": "N", "7": "E", "114": "N", "78": "W", "34": "S", "11": "W", "120": "N", "66": "S", "63": "W", "110": "W", "86": "N", "51": "E", "44": "W", "64": "E", "98": "N", "13": "E", "40": "E", "17": "N", "163": "N", "94": "W", "57": "E", "26": "N", "79": "S", "121": "N", "102": "N", "129": "S", "156": "S", "69": "W", "122": "N", "19": "E", "104": "E", "76": "W", "0": "N", "132": "E", "92": "N", "107": "N", "21": "N", "119": "W", "136": "E", "159": "N", "181": "W", "166": "N", "14": "E", "95": "N", "137": "W", "103": "E", "12": "N", "147": "N", "152": "N", "105": "W", "133": "N", "4": "N", "41": "N", "91": "W", "125": "S", "111": "N", "62": "W", "173": "S", "8": "W", "89": "E", "75": "S", "146": "S", "60": "E", "52": "N", "139": "N", "50": "E", "5": "E", "33": "W", "35": "E", "39": "S", "15": "E", "135": "S", "47": "E", "140": "S", "67": "E", "42": "W", "38": "E", "126": "W", "100": "E", "143": "S", "162": "E", "150": "N", "165": "N", "29": "N", "112": "S", "182": "S", "172": "N", "23": "W", "116": "W"}, {"158": "E", "127": "N", "48": "W", "178": "E", "118": "E", "59": "N", "88": "S", "128": "E", "43": "E", "70": "S", "65": "E", "6": "W", "142": "S", "145": "N", "16": "E", "72": "E", "155": "W", "9": "W", "175": "W", "109": "S", "30": "N", "32": "W", "113": "E", "80": "E", "177": "N", "22": "W", "83": "E", "37": "N", "84": "N", "90": "W", "138": "N", "153": "S", "134": "W", "71": "S", "87": "E", "164": "N", "160": "W", "114": "N", "78": "W", "34": "S", "11": "W", "120": "W", "66": "W", "63": "W", "168": "S", "110": "W", "86": "W", "44": "W", "98": "N", "13": "E", "40": "S", "163": "E", "94": "S", "57": "E", "2": "W", "26": "W", "121": "N", "102": "E", "157": "S", "129": "E", "156": "S", "69": "W", "96": "W", "46": "N", "122": "N", "19": "N", "104": "E", "56": "S", "76": "W", "0": "N", "167": "E", "92": "N", "107": "W", "21": "N", "117": "W", "119": "W", "108": "W", "136": "N", "159": "N", "166": "N", "14": "S", "74": "N", "95": "N", "137": "N", "103": "N", "12": "W", "147": "N", "152": "N", "105": "W", "133": "N", "4": "E", "41": "N", "125": "W", "111": "N", "62": "N", "173": "S", "8": "W", "89": "E", "146": "S", "60": "E", "170": "W", "52": "N", "154": "E", "68": "N", "139": "N", "50": "E", "5": "N", "33": "N", "35": "E", "39": "S", "15": "E", "169": "W", "31": "E", "135": "S", "47": "E", "140": "S", "67": "E", "42": "S", "38": "E", "126": "S", "100": "S", "143": "S", "162": "E", "150": "W", "165": "W", "29": "W", "112": "W", "182": "W", "172": "W", "23": "W", "116": "W"}, {"158": "E", "127": "N", "48": "W", "178": "E", "118": "E", "59": "N", "88": "S", "128": "E", "43": "E", "70": "E", "65": "E", "6": "W", "142": "S", "145": "N", "16": "S", "72": "N", "9": "W", "109": "S", "30": "E", "32": "S", "25": "E", "113": "E", "141": "W", "80": "N", "177": "W", "22": "S", "83": "N", "84": "N", "90": "W", "138": "E", "153": "E", "134": "W", "71": "E", "87": "E", "54": "W", "164": "N", "160": "S", "114": "N", "78": "W", "11": "W", "93": "N", "120": "S", "66": "S", "63": "W", "168": "W", "110": "S", "151": "S", "13": "E", "24": "N", "40": "S", "163": "E", "94": "S", "161": "S", "57": "E", "99": "S", "82": "N", "2": "N", "79": "W", "121": "E", "102": "E", "157": "E", "129": "E", "69": "S", "96": "W", "122": "N", "19": "E", "104": "E", "76": "W", "0": "E", "36": "S", "73": "N", "92": "N", "107": "N", "21": "N", "119": "S", "136": "N", "166": "N", "74": "W", "95": "N", "137": "W", "103": "N", "12": "N", "147": "N", "152": "N", "105": "W", "133": "E", "4": "N", "41": "N", "125": "W", "111": "N", "62": "N", "173": "E", "8": "W", "89": "E", "75": "W", "60": "N", "61": "E", "52": "N", "154": "E", "139": "N", "50": "E", "20": "E", "5": "N", "35": "E", "39": "S", "15": "E", "123": "S", "148": "W", "31": "S", "135": "S", "47": "E", "140": "S", "67": "E", "38": "E", "126": "S", "101": "W", "100": "E", "143": "W", "162": "E", "165": "W", "29": "N", "112": "W", "182": "S", "23": "W", "116": "W"}, {"158": "E", "127": "N", "48": "W", "178": "E", "118": "E", "59": "N", "88": "S", "128": "E", "43": "E", "65": "E", "6": "W", "142": "S", "145": "N", "16": "S", "72": "N", "155": "N", "9": "S", "109": "S", "30": "N", "32": "S", "25": "S", "113": "N", "80": "E", "177": "N", "22": "S", "83": "N", "84": "W", "90": "W", "153": "E", "71": "S", "87": "E", "54": "S", "164": "N", "114": "N", "78": "W", "11": "S", "93": "W", "120": "E", "66": "S", "63": "W", "168": "N", "28": "E", "110": "S", "44": "S", "81": "E", "13": "E", "24": "E", "40": "S", "17": "W", "163": "E", "94": "S", "57": "E", "99": "W", "106": "E", "82": "E", "2": "N", "79": "N", "121": "E", "102": "E", "157": "S", "129": "N", "156": "S", "69": "S", "96": "W", "46": "S", "19": "N", "104": "E", "76": "W", "0": "E", "132": "N", "107": "W", "21": "N", "117": "N", "119": "S", "108": "W", "136": "E", "181": "E", "166": "N", "74": "W", "95": "N", "137": "W", "103": "N", "12": "N", "147": "W", "152": "N", "105": "W", "133": "E", "4": "N", "41": "N", "111": "N", "62": "N", "173": "E", "8": "W", "89": "E", "75": "S", "146": "S", "60": "N", "61": "E", "52": "N", "68": "S", "139": "N", "50": "S", "20": "E", "5": "E", "35": "E", "39": "S", "169": "E", "135": "S", "47": "E", "140": "S", "67": "E", "42": "W", "38": "E", "126": "W", "100": "E", "143": "S", "162": "E", "150": "S", "165": "W", "29": "E", "112": "S", "182": "W", "172": "N", "23": "W", "116": "W"}, {"158": "E", "127": "E", "48": "W", "178": "E", "118": "E", "59": "N", "88": "S", "128": "E", "43": "E", "65": "E", "6": "W", "142": "E", "145": "N", "16": "S", "72": "N", "155": "W", "9": "W", "175": "W", "109": "S", "30": "N", "32": "S", "25": "S", "45": "W", "113": "E", "141": "E", "80": "N", "177": "N", "22": "S", "83": "N", "37": "W", "84": "W", "90": "W", "153": "E", "71": "S", "87": "E", "164": "N", "160": "S", "7": "N", "114": "N", "78": "W", "34": "E", "11": "S", "93": "W", "120": "E", "66": "W", "63": "W", "28": "E", "110": "W", "86": "W", "44": "W", "81": "N", "64": "W", "98": "S", "13": "E", "24": "E", "40": "S", "17": "W", "163": "E", "94": "S", "161": "S", "57": "E", "99": "S", "82": "E", "26": "W", "121": "E", "102": "N", "157": "E", "129": "N", "156": "E", "69": "S", "96": "W", "122": "N", "19": "E", "104": "E", "56": "N", "76": "W", "0": "S", "36": "N", "73": "E", "92": "E", "107": "W", "21": "N", "119": "S", "136": "N", "97": "S", "166": "N", "74": "N", "95": "E", "137": "W", "103": "N", "12": "N", "152": "N", "105": "W", "133": "N", "4": "E", "41": "N", "91": "N", "125": "S", "111": "E", "62": "N", "173": "S", "8": "W", "89": "E", "75": "S", "115": "W", "60": "E", "61": "E", "52": "N", "139": "W", "50": "S", "20": "E", "5": "N", "35": "N", "39": "S", "123": "S", "135": "S", "47": "E", "67": "S", "42": "W", "38": "E", "126": "W", "100": "S", "143": "S", "162": "E", "150": "E", "165": "W", "29": "N", "112": "S", "182": "W", "3": "N", "172": "N", "23": "N", "116": "W"}, {"158": "E", "127": "E", "48": "W", "178": "E", "118": "E", "59": "N", "88": "S", "128": "E", "43": "E", "65": "E", "6": "W", "142": "E", "145": "N", "16": "S", "72": "E", "155": "N", "9": "W", "175": "N", "109": "S", "30": "N", "32": "S", "25": "W", "113": "E", "80": "E", "177": "W", "22": "S", "83": "E", "37": "N", "84": "W", "90": "S", "153": "S", "71": "S", "87": "E", "164": "E", "160": "E", "114": "W", "78": "W", "34": "N", "11": "S", "120": "N", "66": "S", "63": "W", "28": "S", "110": "S", "86": "W", "44": "S", "81": "N", "13": "N", "24": "N", "40": "E", "17": "S", "163": "E", "94": "S", "57": "E", "99": "S", "106": "S", "82": "S", "2": "E", "26": "S", "121": "N", "102": "E", "157": "E", "129": "N", "156": "S", "69": "S", "96": "W", "122": "N", "19": "E", "104": "E", "56": "W", "76": "S", "0": "E", "132": "W", "92": "N", "107": "W", "21": "N", "117": "S", "119": "S", "108": "S", "136": "N", "159": "S", "97": "W", "166": "N", "74": "W", "95": "N", "137": "N", "103": "N", "12": "N", "152": "N", "105": "S", "133": "N", "4": "N", "41": "N", "111": "E", "62": "N", "8": "S", "89": "N", "75": "S", "146": "S", "115": "S", "60": "N", "61": "E", "52": "N", "139": "W", "50": "S", "20": "E", "5": "E", "39": "S", "169": "S", "148": "E", "31": "E", "135": "S", "140": "E", "67": "E", "42": "W", "38": "E", "126": "S", "100": "S", "143": "S", "162": "E", "150": "E", "165": "W", "29": "N", "112": "S", "182": "W", "3": "W", "172": "W", "23": "N"}, {"158": "E", "127": "E", "48": "W", "118": "E", "59": "N", "88": "S", "128": "E", "43": "E", "65": "E", "6": "W", "174": "S", "145": "N", "16": "S", "72": "N", "155": "W", "9": "W", "109": "E", "1": "W", "30": "W", "32": "S", "25": "W", "113": "S", "80": "E", "177": "N", "22": "S", "83": "E", "37": "N", "84": "W", "90": "S", "153": "E", "71": "E", "87": "N", "54": "S", "164": "N", "160": "S", "7": "N", "114": "N", "78": "W", "34": "W", "120": "E", "66": "S", "63": "W", "28": "E", "110": "W", "151": "W", "86": "W", "44": "S", "81": "N", "98": "E", "13": "E", "24": "N", "40": "E", "17": "W", "163": "E", "94": "S", "161": "W", "57": "E", "82": "S", "2": "E", "79": "S", "121": "E", "102": "E", "129": "N", "69": "S", "96": "W", "122": "E", "19": "E", "104": "S", "76": "S", "0": "E", "132": "S", "73": "W", "92": "N", "107": "W", "21": "W", "119": "W", "136": "N", "18": "S", "97": "W", "166": "N", "74": "W", "95": "N", "137": "N", "103": "N", "12": "E", "147": "E", "152": "N", "105": "S", "133": "N", "41": "N", "91": "S", "111": "N", "62": "N", "89": "E", "75": "S", "146": "E", "115": "S", "60": "E", "61": "E", "52": "N", "154": "W", "68": "W", "139": "W", "50": "S", "20": "E", "5": "E", "49": "E", "35": "E", "39": "S", "31": "E", "135": "S", "47": "N", "140": "S", "67": "S", "42": "W", "38": "E", "126": "S", "100": "W", "143": "W", "150": "E", "165": "W", "29": "N", "112": "W", "182": "W", "3": "N", "172": "W", "23": "N"}, {"48": "S", "118": "E", "59": "N", "88": "S", "128": "E", "65": "E", "6": "W", "142": "S", "174": "E", "145": "N", "16": "S", "72": "N", "155": "W", "27": "S", "9": "W", "175": "W", "1": "S", "30": "N", "32": "S", "25": "W", "45": "E", "113": "S", "80": "E", "177": "N", "22": "S", "83": "E", "37": "N", "84": "N", "90": "S", "153": "S", "180": "W", "71": "E", "87": "N", "164": "N", "7": "N", "114": "W", "78": "W", "120": "E", "66": "S", "63": "W", "168": "W", "28": "S", "110": "W", "86": "N", "51": "W", "44": "W", "81": "W", "13": "N", "24": "N", "40": "S", "17": "S", "163": "E", "94": "W", "99": "S", "82": "S", "121": "E", "102": "S", "129": "N", "69": "S", "96": "S", "19": "E", "104": "S", "76": "S", "132": "S", "92": "N", "107": "W", "21": "N", "117": "E", "119": "W", "136": "N", "159": "S", "18": "S", "181": "S", "97": "W", "166": "N", "14": "W", "74": "W", "95": "N", "137": "W", "103": "E", "12": "N", "152": "N", "105": "S", "133": "N", "4": "E", "41": "N", "91": "S", "125": "W", "111": "E", "8": "W", "75": "E", "60": "E", "52": "N", "154": "W", "68": "S", "139": "W", "50": "S", "5": "S", "35": "E", "123": "E", "169": "W", "135": "S", "47": "N", "140": "S", "67": "S", "42": "S", "38": "N", "126": "S", "100": "S", "143": "S", "162": "N", "150": "E", "165": "W", "29": "N", "112": "S", "182": "W", "172": "W", "23": "W", "116": "N"}, {"48": "W", "118": "E", "59": "N", "88": "S", "128": "E", "65": "E", "6": "S", "142": "S", "174": "E", "145": "N", "16": "S", "72": "N", "155": "N", "27": "E", "9": "W", "175": "N", "1": "S", "30": "N", "32": "S", "25": "S", "113": "E", "141": "E", "80": "E", "177": "W", "22": "S", "83": "E", "37": "N", "84": "W", "90": "S", "153": "E", "71": "E", "87": "N", "164": "N", "160": "S", "7": "N", "114": "W", "78": "W", "120": "E", "66": "S", "63": "W", "28": "S", "110": "W", "86": "N", "51": "W", "44": "N", "81": "N", "13": "E", "24": "E", "40": "S", "17": "S", "163": "E", "94": "W", "161": "S", "57": "S", "99": "E", "82": "S", "26": "E", "121": "S", "102": "S", "129": "E", "156": "S", "69": "S", "96": "S", "46": "W", "122": "W", "19": "N", "104": "W", "76": "S", "0": "E", "92": "E", "107": "W", "21": "N", "119": "W", "108": "S", "136": "N", "18": "E", "97": "N", "166": "E", "14": "S", "74": "N", "95": "N", "137": "W", "103": "N", "12": "N", "152": "W", "105": "S", "133": "N", "4": "E", "41": "N", "125": "S", "111": "N", "62": "N", "8": "S", "89": "E", "115": "E", "60": "E", "52": "W", "154": "N", "68": "W", "139": "W", "50": "S", "49": "E", "35": "E", "39": "W", "15": "E", "123": "N", "31": "W", "135": "S", "47": "N", "140": "S", "67": "S", "42": "S", "38": "N", "126": "W", "100": "S", "143": "W", "150": "N", "29": "N", "112": "S", "182": "W", "172": "W", "23": "W", "116": "N"}, {"48": "S", "118": "E", "59": "N", "88": "S", "128": "N", "65": "E", "6": "S", "142": "E", "174": "E", "145": "E", "16": "S", "72": "W", "155": "N", "27": "E", "9": "N", "175": "W", "1": "E", "30": "W", "32": "S", "25": "W", "113": "E", "80": "E", "177": "W", "22": "S", "83": "E", "37": "W", "84": "N", "90": "S", "153": "E", "71": "E", "87": "E", "54": "W", "160": "E", "7": "W", "114": "W", "78": "S", "34": "S", "93": "E", "120": "E", "66": "S", "63": "S", "28": "S", "110": "W", "86": "W", "44": "W", "81": "N", "64": "S", "98": "N", "13": "E", "24": "E", "40": "E", "17": "S", "163": "E", "94": "W", "161": "E", "57": "E", "99": "E", "82": "S", "121": "S", "102": "S", "157": "W", "129": "E", "156": "S", "69": "E", "96": "S", "46": "W", "122": "N", "19": "E", "104": "W", "76": "S", "0": "S", "132": "E", "73": "W", "92": "N", "107": "W", "117": "W", "119": "W", "108": "E", "136": "N", "159": "N", "18": "E", "166": "E", "14": "W", "74": "N", "95": "N", "137": "N", "103": "N", "12": "N", "152": "W", "105": "S", "133": "N", "4": "E", "41": "N", "125": "W", "111": "N", "8": "S", "89": "E", "60": "E", "52": "W", "154": "N", "68": "W", "139": "W", "50": "S", "33": "S", "35": "N", "39": "S", "15": "N", "169": "E", "31": "S", "135": "S", "140": "S", "67": "S", "42": "S", "126": "S", "100": "S", "162": "E", "150": "N", "29": "E", "112": "S", "182": "W", "172": "N", "116": "N"}, {"48": "S", "118": "E", "59": "E", "88": "S", "128": "E", "65": "E", "6": "S", "142": "S", "174": "E", "145": "E", "16": "S", "72": "N", "155": "N", "27": "E", "9": "W", "175": "N", "1": "E", "30": "W", "32": "S", "25": "W", "113": "E", "80": "E", "177": "W", "22": "S", "83": "E", "37": "N", "84": "W", "90": "S", "153": "E", "71": "E", "87": "E", "164": "W", "160": "E", "7": "W", "114": "N", "78": "S", "93": "S", "120": "E", "66": "W", "63": "S", "168": "E", "28": "S", "110": "W", "86": "N", "51": "W", "44": "W", "81": "W", "64": "S", "98": "W", "24": "E", "40": "E", "17": "S", "163": "E", "94": "S", "161": "E", "57": "E", "99": "E", "82": "S", "2": "N", "79": "W", "121": "S", "102": "E", "129": "E", "156": "E", "69": "S", "96": "E", "46": "W", "122": "W", "19": "E", "104": "S", "76": "S", "36": "E", "167": "S", "132": "N", "73": "S", "92": "E", "107": "W", "21": "E", "117": "S", "119": "W", "136": "E", "18": "N", "97": "S", "166": "E", "74": "W", "95": "N", "137": "W", "103": "N", "12": "N", "152": "W", "105": "S", "133": "E", "4": "N", "41": "N", "125": "S", "111": "N", "62": "S", "8": "S", "89": "E", "146": "S", "60": "E", "170": "W", "52": "N", "154": "N", "68": "W", "139": "N", "50": "S", "5": "S", "35": "E", "39": "S", "15": "E", "169": "N", "31": "E", "135": "E", "47": "N", "140": "S", "67": "S", "42": "W", "126": "S", "100": "S", "143": "E", "162": "E", "165": "N", "29": "N", "112": "S", "182": "W", "3": "N", "172": "N", "53": "E", "116": "N"}, {"48": "S", "118": "N", "59": "E", "88": "W", "128": "E", "65": "N", "55": "S", "6": "S", "142": "S", "174": "N", "145": "E", "16": "S", "72": "N", "155": "N", "27": "E", "9": "N", "175": "N", "1": "E", "30": "W", "32": "S", "25": "W", "141": "W", "80": "N", "177": "S", "22": "S", "37": "N", "84": "S", "90": "S", "153": "E", "71": "S", "87": "E", "164": "N", "160": "E", "7": "S", "114": "N", "78": "S", "11": "N", "144": "S", "93": "S", "66": "S", "63": "S", "28": "S", "110": "W", "151": "S", "86": "N", "44": "W", "81": "W", "64": "E", "98": "S", "13": "N", "24": "S", "130": "S", "40": "E", "17": "S", "163": "E", "94": "W", "161": "E", "57": "E", "99": "E", "106": "N", "82": "S", "2": "E", "79": "N", "121": "S", "102": "E", "156": "E", "69": "W", "96": "S", "122": "W", "19": "E", "104": "S", "76": "S", "167": "E", "73": "S", "92": "E", "107": "W", "21": "N", "117": "S", "119": "W", "136": "E", "18": "E", "181": "W", "166": "E", "74": "W", "95": "N", "137": "N", "103": "N", "12": "W", "152": "W", "105": "S", "133": "E", "4": "E", "41": "W", "125": "E", "111": "N", "62": "E", "8": "W", "89": "N", "60": "E", "61": "S", "170": "S", "52": "W", "154": "N", "139": "W", "50": "S", "5": "E", "35": "E", "39": "S", "15": "S", "169": "E", "135": "S", "47": "E", "140": "S", "67": "S", "42": "W", "38": "E", "126": "S", "101": "E", "100": "S", "143": "N", "162": "E", "150": "E", "29": "E", "112": "S", "182": "W", "172": "N", "53": "S", "116": "W"}, {"48": "S", "118": "N", "59": "E", "88": "W", "128": "S", "65": "N", "55": "E", "6": "S", "142": "E", "174": "E", "16": "S", "72": "N", "155": "N", "27": "E", "9": "N", "124": "E", "175": "N", "1": "S", "30": "N", "32": "S", "25": "W", "179": "N", "80": "N", "177": "S", "22": "S", "83": "N", "37": "N", "90": "S", "153": "E", "180": "S", "134": "E", "71": "E", "87": "E", "160": "E", "7": "W", "114": "N", "78": "S", "11": "N", "144": "E", "93": "E", "120": "W", "66": "W", "63": "S", "28": "W", "110": "W", "151": "S", "86": "N", "51": "E", "44": "W", "81": "W", "64": "N", "13": "N", "24": "S", "40": "S", "94": "S", "161": "E", "57": "E", "99": "E", "106": "N", "82": "E", "2": "N", "79": "N", "121": "S", "102": "S", "157": "E", "129": "W", "156": "E", "69": "S", "96": "S", "19": "E", "104": "S", "76": "S", "36": "S", "167": "E", "73": "E", "92": "N", "107": "W", "21": "N", "117": "S", "119": "W", "108": "N", "136": "S", "18": "E", "181": "W", "166": "E", "74": "W", "95": "E", "137": "N", "103": "N", "12": "N", "152": "W", "105": "S", "133": "N", "4": "N", "41": "W", "91": "S", "125": "E", "111": "N", "8": "S", "89": "N", "146": "S", "60": "N", "61": "S", "170": "S", "52": "N", "154": "W", "68": "N", "50": "S", "20": "S", "5": "S", "33": "N", "35": "E", "39": "S", "15": "E", "123": "S", "169": "E", "31": "N", "135": "E", "47": "E", "140": "E", "67": "S", "42": "S", "38": "E", "126": "S", "100": "W", "143": "E", "162": "N", "150": "E", "165": "N", "29": "E", "112": "S", "182": "W", "3": "N", "172": "N", "53": "S", "23": "N", "116": "W"}, {"48": "S", "118": "N", "88": "W", "128": "S", "65": "N", "55": "S", "6": "S", "142": "E", "174": "E", "16": "W", "72": "N", "155": "N", "27": "E", "9": "N", "175": "N", "1": "S", "32": "S", "25": "W", "179": "E", "80": "E", "177": "W", "22": "W", "83": "E", "37": "N", "90": "W", "153": "E", "180": "E", "71": "E", "87": "E", "160": "E", "7": "S", "114": "W", "78": "S", "11": "N", "144": "E", "93": "S", "120": "W", "66": "S", "63": "S", "28": "S", "110": "W", "151": "S", "86": "N", "51": "E", "44": "S", "81": "S", "98": "W", "13": "E", "24": "E", "130": "S", "40": "S", "17": "W", "94": "S", "161": "E", "57": "E", "99": "E", "106": "E", "82": "E", "2": "E", "79": "E", "121": "S", "102": "E", "129": "N", "156": "E", "96": "S", "46": "W", "122": "N", "19": "N", "104": "W", "76": "S", "36": "E", "167": "N", "132": "N", "73": "E", "92": "W", "107": "W", "21": "W", "119": "W", "108": "E", "136": "S", "18": "E", "181": "S", "97": "E", "166": "E", "74": "S", "95": "E", "137": "N", "103": "E", "12": "N", "152": "N", "105": "S", "133": "W", "4": "N", "41": "W", "91": "S", "125": "E", "111": "N", "62": "E", "8": "S", "89": "E", "75": "S", "146": "E", "61": "E", "170": "S", "52": "N", "154": "N", "139": "N", "50": "S", "20": "S", "5": "E", "35": "E", "39": "S", "15": "E", "123": "E", "169": "E", "31": "E", "135": "E", "47": "E", "140": "E", "67": "S", "42": "S", "38": "E", "126": "S", "101": "W", "100": "S", "143": "E", "162": "E", "150": "E", "165": "W", "29": "E", "112": "S", "182": "W", "3": "W", "172": "W", "53": "S", "23": "W", "116": "W"}, {"48": "S", "118": "E", "88": "S", "128": "S", "65": "E", "55": "W", "6": "S", "142": "E", "174": "E", "16": "W", "72": "N", "155": "N", "27": "E", "9": "N", "175": "N", "1": "S", "25": "W", "179": "E", "45": "S", "141": "S", "80": "E", "177": "W", "22": "W", "83": "E", "37": "N", "90": "S", "153": "E", "180": "E", "134": "W", "71": "E", "87": "N", "164": "N", "160": "E", "7": "S", "114": "W", "78": "S", "144": "N", "93": "W", "120": "S", "66": "S", "63": "S", "28": "S", "110": "N", "151": "S", "86": "W", "51": "E", "81": "S", "64": "E", "13": "E", "24": "E", "130": "E", "40": "E", "17": "W", "94": "S", "161": "E", "57": "E", "99": "E", "106": "E", "82": "S", "2": "S", "121": "E", "102": "E", "129": "N", "156": "E", "96": "E", "46": "W", "122": "N", "19": "W", "104": "W", "76": "S", "0": "S", "167": "N", "73": "S", "92": "N", "107": "S", "21": "N", "119": "W", "136": "S", "18": "N", "97": "S", "166": "E", "74": "S", "95": "S", "137": "N", "103": "E", "12": "N", "147": "W", "152": "N", "133": "N", "4": "N", "41": "S", "91": "E", "125": "E", "111": "N", "62": "E", "173": "S", "8": "S", "89": "E", "75": "E", "146": "E", "60": "N", "52": "N", "154": "N", "139": "W", "50": "S", "20": "S", "5": "N", "35": "E", "39": "S", "15": "S", "123": "E", "169": "N", "31": "S", "135": "E", "47": "E", "140": "E", "67": "S", "42": "W", "38": "E", "126": "S", "100": "W", "143": "E", "162": "E", "150": "E", "165": "W", "29": "N", "182": "W", "3": "W", "172": "W", "53": "S", "23": "W", "116": "W"}, {"48": "S", "118": "N", "88": "S", "65": "N", "55": "N", "6": "S", "142": "E", "174": "E", "16": "W", "72": "W", "155": "N", "27": "E", "9": "E", "124": "S", "175": "N", "32": "W", "25": "S", "179": "S", "80": "N", "177": "W", "22": "S", "83": "S", "37": "N", "90": "S", "153": "E", "180": "E", "71": "E", "87": "E", "54": "E", "164": "N", "160": "E", "114": "W", "11": "S", "144": "N", "93": "S", "66": "S", "63": "S", "28": "S", "110": "N", "151": "S", "86": "N", "51": "E", "44": "S", "81": "W", "98": "W", "13": "N", "24": "E", "130": "E", "40": "E", "94": "S", "161": "E", "57": "S", "99": "S", "106": "E", "82": "E", "121": "S", "102": "E", "157": "N", "129": "N", "156": "E", "96": "S", "122": "W", "19": "S", "104": "S", "76": "S", "0": "E", "167": "N", "73": "W", "92": "W", "107": "S", "21": "E", "117": "S", "119": "W", "108": "N", "136": "S", "18": "N", "181": "N", "97": "S", "166": "E", "14": "E", "74": "S", "95": "S", "137": "N", "103": "N", "12": "E", "152": "W", "105": "E", "133": "W", "4": "N", "41": "W", "91": "E", "125": "E", "111": "N", "173": "S", "89": "N", "75": "S", "146": "E", "115": "W", "60": "N", "61": "E", "170": "S", "52": "W", "154": "E", "68": "E", "139": "W", "50": "S", "20": "E", "5": "E", "33": "S", "35": "S", "39": "S", "15": "S", "123": "N", "31": "W", "135": "E", "47": "E", "140": "E", "67": "S", "42": "W", "38": "E", "126": "S", "100": "S", "143": "S", "162": "E", "150": "E", "165": "W", "29": "N", "112": "W", "182": "N", "3": "W", "172": "W", "53": "S", "23": "W", "116": "W"}, {"48": "S", "118": "E", "88": "W", "65": "E", "6": "S", "142": "E", "174": "E", "72": "W", "155": "E", "27": "E", "124": "W", "175": "N", "32": "S", "25": "S", "179": "E", "141": "S", "80": "W", "177": "W", "22": "S", "83": "E", "37": "N", "153": "E", "180": "S", "134": "W", "71": "S", "87": "E", "164": "N", "160": "E", "7": "S", "114": "W", "11": "S", "144": "E", "93": "S", "120": "E", "66": "S", "63": "W", "28": "S", "110": "N", "151": "S", "86": "E", "44": "W", "81": "W", "64": "S", "98": "W", "24": "S", "130": "E", "40": "S", "17": "E", "163": "W", "94": "W", "161": "E", "57": "S", "99": "E", "106": "N", "82": "S", "2": "S", "79": "W", "121": "S", "102": "N", "157": "W", "129": "N", "156": "S", "96": "S", "46": "E", "19": "S", "104": "S", "56": "W", "76": "W", "0": "S", "167": "E", "132": "S", "73": "S", "92": "W", "107": "S", "21": "N", "117": "S", "119": "W", "136": "S", "18": "N", "166": "N", "14": "N", "74": "S", "95": "S", "137": "N", "103": "N", "12": "E", "152": "W", "133": "W", "4": "N", "41": "S", "125": "S", "111": "E", "62": "W", "173": "W", "8": "S", "89": "E", "146": "E", "61": "S", "170": "E", "52": "N", "154": "E", "139": "W", "50": "S", "20": "N", "35": "S", "39": "S", "15": "S", "31": "S", "135": "E", "140": "E", "67": "S", "42": "S", "38": "S", "126": "S", "100": "S", "143": "E", "162": "E", "150": "S", "165": "W", "29": "E", "112": "S", "182": "N", "3": "W", "172": "W", "53": "S", "23": "W", "116": "W"}, {"48": "S", "118": "N", "88": "N", "55": "N", "6": "S", "142": "E", "72": "W", "155": "E", "27": "E", "124": "N", "175": "E", "32": "S", "25": "S", "179": "E", "45": "N", "177": "W", "22": "S", "83": "S", "37": "N", "90": "W", "153": "E", "180": "E", "71": "S", "87": "E", "164": "N", "160": "E", "7": "S", "114": "W", "11": "S", "144": "E", "93": "S", "66": "S", "63": "W", "28": "S", "110": "W", "151": "S", "44": "W", "81": "W", "64": "W", "98": "S", "13": "N", "24": "E", "130": "E", "40": "S", "17": "S", "163": "N", "161": "E", "99": "E", "106": "E", "121": "E", "102": "E", "157": "S", "129": "E", "156": "E", "96": "S", "122": "W", "104": "S", "56": "S", "76": "S", "0": "E", "36": "S", "132": "S", "73": "S", "107": "S", "21": "W", "119": "W", "108": "W", "136": "E", "159": "S", "18": "E", "181": "S", "97": "W", "166": "N", "14": "N", "74": "S", "95": "S", "137": "N", "103": "W", "12": "E", "147": "E", "152": "W", "133": "N", "4": "E", "41": "S", "125": "E", "173": "S", "8": "S", "89": "E", "75": "S", "146": "E", "115": "E", "60": "E", "61": "S", "52": "W", "154": "N", "139": "W", "50": "S", "49": "W", "35": "S", "39": "E", "15": "S", "148": "N", "31": "S", "135": "S", "140": "S", "67": "S", "42": "W", "38": "E", "126": "S", "101": "E", "100": "S", "143": "E", "162": "E", "150": "S", "165": "W", "29": "E", "112": "S", "182": "N", "3": "W", "172": "W", "53": "S", "23": "W", "116": "W"}, {"48": "E", "142": "E", "155": "E", "27": "E", "32": "S", "25": "S", "179": "E", "177": "S", "22": "S", "37": "N", "90": "S", "153": "E", "180": "E", "134": "E", "71": "W", "87": "E", "54": "E", "164": "N", "160": "E", "7": "E", "114": "W", "144": "E", "93": "S", "120": "W", "66": "S", "63": "S", "28": "S", "110": "N", "44": "W", "81": "W", "64": "N", "98": "S", "13": "N", "24": "E", "130": "E", "40": "W", "17": "E", "161": "E", "99": "E", "106": "E", "79": "E", "121": "E", "102": "S", "129": "E", "156": "E", "96": "E", "46": "E", "122": "W", "104": "S", "56": "S", "76": "S", "0": "E", "73": "S", "92": "W", "107": "S", "21": "N", "117": "W", "119": "W", "136": "E", "159": "S", "18": "N", "181": "E", "97": "W", "166": "N", "74": "S", "95": "S", "137": "E", "103": "W", "12": "S", "152": "W", "105": "S", "133": "W", "4": "E", "91": "S", "125": "E", "173": "S", "8": "S", "89": "N", "75": "S", "146": "S", "60": "E", "61": "E", "52": "W", "154": "N", "139": "W", "50": "S", "5": "S", "33": "N", "35": "E", "39": "S", "15": "S", "148": "E", "31": "S", "135": "E", "140": "E", "67": "S", "42": "W", "38": "E", "126": "S", "100": "S", "143": "E", "162": "N", "165": "W", "29": "S", "112": "S", "182": "W", "3": "W", "172": "W", "53": "S", "23": "W", "116": "W"}, {"142": "E", "27": "E", "175": "N", "32": "E", "25": "S", "179": "E", "141": "N", "177": "S", "22": "E", "37": "N", "90": "S", "153": "E", "180": "E", "87": "N", "164": "N", "160": "E", "7": "E", "114": "S", "78": "N", "144": "N", "93": "S", "66": "S", "63": "S", "168": "N", "28": "S", "110": "N", "151": "S", "86": "E", "44": "W", "81": "W", "64": "W", "98": "S", "13": "E", "24": "S", "130": "N", "171": "E", "17": "E", "163": "N", "94": "S", "161": "E", "99": "N", "106": "E", "121": "E", "102": "S", "157": "N", "129": "N", "156": "E", "96": "E", "46": "E", "122": "W", "19": "N", "104": "S", "56": "S", "76": "S", "0": "E", "73": "S", "107": "S", "21": "W", "119": "W", "136": "E", "18": "N", "166": "E", "74": "S", "95": "E", "137": "E", "103": "N", "12": "S", "147": "E", "152": "W", "105": "S", "133": "N", "4": "N", "125": "E", "111": "W", "62": "W", "8": "S", "89": "N", "146": "E", "60": "E", "61": "E", "170": "S", "52": "W", "154": "N", "68": "W", "139": "W", "50": "S", "20": "N", "5": "S", "35": "E", "39": "S", "15": "S", "123": "N", "148": "E", "31": "S", "135": "E", "47": "S", "140": "E", "67": "S", "42": "W", "38": "E", "126": "S", "101": "W", "100": "W", "165": "W", "29": "S", "112": "S", "182": "N", "3": "W", "172": "W", "53": "W", "23": "W", "116": "W"}, {"142": "E", "27": "E", "175": "N", "25": "S", "45": "S", "141": "N", "177": "S", "22": "E", "37": "E", "90": "S", "153": "E", "180": "E", "87": "N", "160": "E", "144": "E", "93": "S", "66": "E", "63": "S", "28": "S", "110": "N", "151": "S", "86": "E", "44": "W", "81": "W", "64": "N", "98": "S", "13": "N", "24": "E", "130": "E", "171": "E", "17": "E", "94": "S", "161": "E", "99": "E", "106": "E", "121": "S", "157": "E", "129": "E", "156": "E", "96": "E", "46": "E", "122": "W", "104": "S", "56": "S", "76": "S", "36": "E", "167": "N", "132": "S", "73": "S", "107": "S", "21": "W", "119": "N", "108": "E", "136": "S", "159": "N", "18": "E", "181": "N", "166": "E", "14": "E", "74": "S", "95": "E", "137": "N", "103": "N", "12": "S", "152": "W", "105": "S", "133": "N", "4": "N", "125": "E", "111": "N", "173": "N", "149": "N", "8": "S", "89": "E", "75": "N", "146": "E", "60": "E", "61": "E", "170": "E", "52": "W", "154": "N", "139": "W", "50": "S", "20": "E", "35": "S", "39": "S", "15": "S", "148": "N", "31": "S", "135": "E", "47": "E", "140": "E", "67": "S", "42": "S", "38": "E", "126": "S", "100": "S", "143": "E", "162": "E", "150": "W", "165": "W", "29": "S", "112": "S", "182": "N", "3": "W", "172": "W", "53": "S", "116": "W"}, {"142": "E", "27": "E", "175": "N", "25": "W", "177": "S", "90": "S", "153": "E", "180": "E", "87": "E", "164": "E", "160": "E", "144": "E", "93": "S", "66": "E", "63": "S", "168": "S", "28": "S", "110": "N", "44": "N", "81": "S", "64": "E", "176": "N", "98": "E", "13": "N", "24": "E", "130": "S", "163": "S", "94": "S", "161": "E", "99": "N", "106": "E", "26": "W", "121": "S", "157": "E", "156": "E", "96": "E", "122": "W", "104": "S", "56": "S", "76": "S", "36": "N", "73": "S", "107": "S", "21": "W", "117": "E", "119": "N", "136": "S", "159": "N", "181": "N", "97": "S", "166": "E", "74": "S", "95": "E", "137": "E", "103": "N", "12": "E", "152": "W", "133": "W", "4": "N", "91": "N", "125": "E", "111": "W", "62": "W", "173": "N", "149": "E", "8": "S", "89": "E", "75": "N", "146": "E", "60": "E", "52": "W", "154": "E", "68": "E", "139": "W", "50": "W", "20": "E", "35": "E", "39": "E", "15": "S", "169": "E", "148": "E", "31": "S", "135": "E", "47": "E", "140": "N", "67": "S", "42": "E", "38": "E", "126": "S", "100": "W", "143": "E", "162": "E", "29": "E", "112": "W", "182": "N", "172": "W", "53": "W", "23": "N", "116": "W"}, {"142": "N", "27": "E", "175": "N", "25": "S", "45": "N", "177": "S", "37": "E", "90": "E", "153": "E", "180": "E", "87": "N", "160": "N", "78": "S", "144": "S", "93": "S", "66": "E", "63": "S", "168": "E", "28": "S", "110": "N", "151": "S", "86": "E", "44": "N", "81": "S", "176": "N", "98": "E", "13": "E", "24": "E", "163": "S", "94": "S", "161": "E", "99": "E", "106": "E", "121": "W", "157": "S", "129": "S", "156": "E", "96": "E", "46": "E", "122": "W", "104": "S", "56": "S", "76": "S", "36": "W", "73": "S", "107": "W", "21": "W", "117": "E", "119": "N", "136": "S", "159": "N", "181": "E", "166": "S", "74": "S", "95": "E", "137": "E", "103": "N", "12": "S", "152": "W", "133": "N", "4": "W", "91": "E", "125": "E", "111": "N", "62": "W", "173": "N", "149": "E", "8": "S", "89": "N", "75": "N", "146": "E", "60": "N", "170": "W", "52": "W", "154": "E", "68": "E", "139": "W", "50": "W", "20": "S", "49": "E", "35": "E", "39": "E", "15": "S", "123": "N", "169": "S", "148": "E", "31": "W", "135": "N", "47": "S", "140": "E", "67": "S", "42": "E", "38": "E", "126": "S", "100": "S", "143": "N", "162": "N", "150": "E", "165": "S", "29": "S", "112": "S", "182": "N", "3": "S", "172": "W", "53": "S", "23": "W", "116": "W"}, {"142": "N", "27": "E", "175": "E", "25": "E", "177": "S", "90": "S", "153": "E", "180": "E", "87": "N", "164": "N", "160": "E", "93": "S", "66": "E", "63": "S", "28": "W", "151": "E", "44": "N", "98": "E", "13": "S", "24": "S", "130": "N", "171": "W", "94": "S", "161": "E", "99": "E", "106": "E", "157": "E", "156": "E", "96": "E", "122": "W", "104": "S", "56": "S", "76": "S", "167": "N", "73": "S", "107": "S", "21": "W", "119": "N", "159": "N", "18": "W", "97": "W", "166": "S", "74": "S", "95": "E", "137": "E", "103": "W", "12": "S", "152": "N", "133": "W", "4": "W", "91": "E", "125": "E", "173": "N", "149": "N", "8": "S", "89": "N", "75": "N", "146": "E", "115": "E", "60": "N", "170": "N", "52": "W", "154": "E", "68": "E", "139": "W", "50": "W", "20": "E", "49": "N", "35": "E", "15": "S", "148": "N", "31": "S", "135": "E", "140": "S", "67": "W", "42": "E", "38": "E", "126": "S", "100": "W", "143": "E", "162": "N", "29": "E", "112": "S", "182": "N", "172": "W", "23": "W", "116": "W"}, {"142": "N", "27": "N", "177": "W", "153": "N", "180": "E", "87": "W", "164": "E", "160": "E", "78": "N", "93": "W", "63": "S", "28": "S", "86": "E", "44": "N", "176": "S", "98": "N", "13": "W", "24": "E", "163": "N", "94": "S", "161": "N", "99": "N", "106": "E", "26": "E", "156": "E", "96": "E", "46": "E", "122": "W", "19": "W", "104": "W", "56": "S", "76": "S", "167": "N", "73": "S", "107": "S", "119": "N", "159": "N", "166": "S", "74": "S", "95": "E", "137": "E", "103": "N", "12": "S", "152": "W", "105": "N", "133": "W", "4": "N", "91": "E", "125": "E", "173": "N", "149": "N", "8": "S", "89": "N", "75": "N", "146": "E", "60": "W", "170": "N", "52": "S", "154": "E", "68": "E", "139": "S", "50": "W", "20": "S", "5": "N", "49": "E", "35": "S", "39": "E", "15": "S", "148": "E", "31": "W", "135": "N", "140": "E", "67": "W", "42": "E", "38": "N", "126": "E", "101": "N", "100": "W", "143": "E", "29": "E", "112": "S", "182": "N", "3": "W", "172": "W", "53": "S", "23": "W", "116": "W"}, {"142": "E", "27": "N", "124": "S", "177": "W", "153": "N", "180": "E", "134": "S", "164": "S", "160": "N", "28": "S", "176": "S", "130": "S", "171": "W", "94": "S", "161": "N", "99": "N", "106": "S", "79": "E", "156": "E", "122": "S", "19": "S", "104": "S", "56": "W", "76": "S", "36": "S", "73": "S", "107": "S", "21": "S", "119": "N", "159": "N", "18": "W", "166": "E", "95": "S", "103": "N", "12": "E", "152": "W", "133": "W", "4": "N", "125": "E", "173": "N", "149": "E", "8": "S", "89": "W", "75": "N", "146": "E", "115": "W", "60": "N", "170": "N", "52": "S", "154": "E", "68": "S", "139": "W", "50": "W", "20": "S", "5": "E", "33": "S", "49": "E", "35": "S", "15": "E", "169": "W", "148": "S", "31": "S", "135": "E", "140": "E", "67": "W", "42": "E", "38": "E", "126": "E", "100": "S", "143": "E", "165": "W", "29": "E", "112": "S", "182": "N", "3": "W", "172": "W", "53": "W", "23": "W", "116": "W"}, {"142": "E", "27": "N", "177": "S", "153": "N", "180": "E", "160": "E", "78": "S", "28": "W", "130": "S", "163": "S", "94": "E", "99": "E", "156": "E", "122": "S", "19": "E", "104": "S", "56": "S", "76": "S", "167": "S", "73": "S", "107": "S", "119": "N", "159": "N", "97": "E", "166": "E", "74": "S", "95": "E", "103": "N", "12": "E", "152": "W", "105": "S", "133": "W", "4": "N", "125": "E", "173": "N", "149": "S", "8": "S", "89": "N", "75": "N", "60": "N", "61": "N", "170": "N", "154": "E", "139": "W", "50": "S", "20": "E", "5": "E", "49": "E", "35": "S", "39": "S", "15": "S", "148": "S", "31": "S", "135": "E", "47": "N", "140": "N", "67": "W", "42": "E", "38": "N", "126": "E", "101": "S", "100": "W", "143": "E", "162": "E", "150": "N", "165": "W", "29": "E", "112": "S", "182": "N", "3": "W", "172": "S", "23": "W", "116": "W"}, {"142": "E", "177": "S", "153": "E", "180": "N", "160": "N", "78": "S", "28": "N", "163": "E", "99": "E", "156": "N", "19": "N", "104": "S", "56": "S", "76": "S", "167": "S", "73": "S", "119": "N", "159": "N", "95": "E", "103": "W", "12": "E", "152": "W", "105": "S", "133": "W", "4": "N", "173": "N", "149": "S", "8": "S", "89": "N", "75": "N", "115": "W", "60": "W", "61": "N", "170": "W", "154": "E", "139": "W", "50": "S", "20": "N", "5": "S", "49": "E", "35": "S", "39": "E", "15": "W", "148": "E", "67": "W", "42": "E", "38": "E", "126": "E", "101": "S", "100": "W", "143": "E", "150": "N", "165": "W", "29": "S", "112": "S", "182": "N", "3": "W", "172": "S", "53": "S", "23": "S", "116": "S"}, {"124": "N", "177": "S", "153": "N", "180": "N", "134": "N", "160": "N", "163": "E", "161": "N", "99": "N", "156": "E", "104": "S", "56": "S", "76": "S", "167": "S", "73": "S", "119": "N", "159": "N", "181": "W", "95": "E", "103": "W", "12": "E", "147": "W", "152": "S", "105": "S", "133": "N", "4": "N", "173": "N", "149": "S", "8": "S", "89": "N", "115": "W", "60": "W", "61": "E", "170": "N", "139": "S", "50": "W", "20": "N", "49": "E", "35": "E", "39": "E", "15": "W", "148": "S", "31": "W", "67": "S", "38": "N", "126": "E", "100": "W", "143": "N", "165": "W", "29": "E", "112": "S", "182": "N", "3": "W", "172": "S", "53": "W", "23": "S", "116": "S"}, {"177": "E", "79": "E", "156": "E", "104": "S", "56": "E", "76": "S", "73": "S", "119": "N", "95": "E", "103": "W", "12": "E", "152": "W", "133": "W", "4": "N", "8": "W", "89": "W", "60": "W", "61": "S", "170": "E", "139": "W", "50": "W", "20": "E", "49": "E", "35": "S", "39": "E", "15": "W", "31": "W", "67": "S", "38": "N", "126": "S", "101": "E", "100": "W", "165": "S", "29": "E", "112": "S", "182": "N", "3": "S", "172": "W", "53": "W", "23": "S", "116": "S"}, {"177": "E", "79": "E", "156": "E", "104": "W", "56": "E", "76": "S", "119": "N", "95": "E", "103": "N", "12": "E", "152": "W", "133": "W", "4": "W", "8": "S", "89": "N", "60": "N", "61": "E", "170": "E", "139": "W", "50": "S", "20": "E", "49": "E", "35": "W", "39": "N", "15": "S", "169": "N", "67": "S", "38": "N", "126": "E", "101": "E", "100": "W", "162": "E", "165": "W", "29": "E", "112": "E", "182": "N", "172": "W", "53": "W", "116": "S"}, {"156": "E", "104": "S", "56": "N", "76": "S", "73": "S", "119": "N", "181": "E", "95": "E", "103": "W", "12": "E", "152": "W", "133": "W", "4": "N", "8": "S", "89": "N", "60": "W", "139": "S", "50": "W", "20": "E", "33": "S", "49": "E", "35": "S", "39": "E", "15": "W", "47": "N", "67": "S", "38": "N", "126": "E", "101": "N", "100": "W", "162": "N", "165": "S", "29": "E", "112": "E", "182": "N", "3": "S", "172": "S", "23": "S", "116": "S"}, {"156": "E", "104": "W", "76": "S", "73": "S", "95": "E", "103": "W", "12": "E", "152": "S", "133": "W", "4": "N", "8": "S", "60": "N", "61": "E", "139": "S", "50": "N", "20": "E", "49": "E", "35": "S", "15": "S", "67": "S", "38": "N", "126": "N", "101": "W", "100": "W", "165": "S", "29": "E", "112": "S", "182": "N", "3": "S", "172": "S", "23": "S", "116": "S"}, {"156": "E", "104": "W", "76": "E", "95": "E", "103": "W", "12": "E", "152": "W", "133": "W", "4": "N", "8": "S", "139": "S", "50": "E", "20": "E", "33": "N", "49": "E", "35": "S", "15": "S", "67": "W", "38": "W", "100": "W", "165": "S", "29": "E", "112": "E", "182": "N", "172": "S", "23": "S", "116": "W"}, {"156": "N", "104": "W", "73": "N", "95": "E", "103": "W", "12": "E", "152": "W", "133": "W", "4": "N", "8": "S", "61": "N", "139": "S", "20": "S", "33": "N", "49": "E", "35": "S", "15": "S", "67": "W", "38": "N", "100": "W", "165": "S", "29": "S", "112": "E", "182": "N", "172": "S", "23": "S", "116": "S"}, {"156": "N", "104": "W", "73": "N", "95": "E", "103": "W", "12": "E", "152": "S", "133": "W", "4": "W", "8": "E", "61": "W", "20": "W", "49": "E", "35": "W", "15": "S", "67": "W", "38": "N", "100": "N", "165": "S", "29": "E", "112": "E", "182": "N", "172": "W", "53": "N", "23": "W", "116": "S"}, {"156": "W", "104": "W", "95": "S", "103": "W", "12": "S", "152": "S", "133": "S", "4": "W", "8": "E", "61": "S", "20": "S", "49": "E", "15": "W", "67": "N", "38": "W", "101": "W", "100": "N", "165": "W", "29": "S", "112": "E", "182": "N", "172": "S", "53": "N", "23": "S", "116": "S"}, {"156": "W", "104": "N", "95": "S", "103": "S", "12": "E", "152": "S", "133": "S", "4": "W", "61": "S", "20": "S", "49": "E", "67": "W", "100": "N", "165": "S", "29": "E", "112": "E", "182": "N", "172": "S", "23": "S", "116": "S"}, {"104": "N", "95": "S", "103": "S", "12": "E", "4": "S", "49": "S", "67": "W", "165": "S", "29": "E", "112": "E", "182": "N", "172": "E", "116": "S"}, {"4": "S", "20": "W", "67": "W", "165": "S", "29": "E", "112": "E", "182": "E", "172": "E", "116": "S"}, {"67": "W", "165": "S", "29": "E", "112": "N", "182": "E", "172": "E", "116": "S"}, {"67": "N", "165": "E", "29": "S", "182": "E", "116": "S"}, {"165": "E", "29": "S", "116": "S"}, {"29": "S", "116": "S"}, {"29": "S", "116": "E"}, {"29": "S", "116": "E"}, {"29": "W"}], "result": "SUCCESS", "makespan": 69, "sum": 6363, "algo_name": "OutAndInByPercentage_rand_BIT_", "extra": {"arrival_order": [158, 131, 127, 10, 77, 48, 178, 118, 59, 88, 128, 43, 70, 65, 55, 6, 142, 174, 145, 16, 72, 155, 27, 9, 124, 175, 58, 109, 1, 30, 32, 25, 179, 45, 113, 141, 80, 177, 22, 83, 85, 37, 84, 90, 138, 153, 180, 134, 71, 87, 54, 164, 160, 7, 114, 78, 34, 11, 144, 93, 120, 66, 63, 168, 28, 110, 151, 86, 51, 44, 81, 64, 176, 98, 13, 24, 130, 171, 40, 17, 163, 94, 161, 57, 99, 106, 82, 2, 26, 79, 121, 102, 157, 129, 156, 69, 96, 46, 122, 19, 104, 56, 76, 0, 36, 167, 132, 73, 92, 107, 21, 117, 119, 108, 136, 159, 18, 181, 97, 166, 14, 74, 95, 137, 103, 12, 147, 152, 105, 133, 4, 41, 91, 125, 111, 62, 173, 149, 8, 89, 75, 146, 115, 60, 61, 170, 52, 154, 68, 139, 50, 20, 5, 33, 49, 35, 39, 15, 123, 169, 148, 31, 135, 47, 140, 67, 42, 38, 126, 101, 100, 143, 162, 150, 165, 29, 112, 182, 3, 172, 53, 23, 116], "time_arrived": [2493, 687, 2083, 4466, 3217, 3719, 377, 1329, 3372, 603, 92, 1421, 3056, 1823, 2875, 3855, 492, 1907, 2816, 2366, 3701, 2655, 947, 4567, 1851, 776, 2098, 570, 1580, 4351, 719, 3928, 756, 3724, 1406, 3788, 2497, 1016, 4102, 3824, 1886, 3230, 4064, 291, 1712, 804, 2302, 3977, 140, 3750, 3676, 1676, 3568, 4537, 1259, 349, 2436, 2006, 661, 217, 3508, 3529, 3316, 1543, 1760, 336, 1513, 4043, 3602, 2256, 310, 1196, 521, 2555, 2905, 3433, 2477, 106, 1387, 2111, 868, 1737, 2076, 970, 1046, 984, 1659, 1232, 241, 3415, 1078, 3246, 2585, 1453, 1959, 2946, 2276, 2842, 1790, 2030, 4187, 4140, 2166, 3022, 2404, 3136, 2054, 2617, 2733, 678, 1609, 3307, 4397, 829, 1364, 3468, 4612, 2678, 188, 2721, 1478, 2143, 2343, 3878, 613, 3272, 4131, 82, 270, 2198, 1862, 58, 2529, 3178, 1172, 3953, 2757, 2981, 1099, 3642, 4004, 843, 414, 4212, 1434, 461, 3461, 3071, 3904, 3331, 4273, 1629, 3113, 1137, 3589, 550, 2237, 2179, 36, 2783, 1315, 1988, 4250, 1925, 1284, 4317, 2865, 2509, 1551, 3891, 3537, 1868, 4515, 3323, 431, 647, 1769, 911, 157, 787, 1159, 2825, 4436], "BIT_runs": 1, "old_makespan": 4612, "old_sum": 5659, "improved": "[158, 131, 127, 10, 77, 48, 178, 118, 59, 88, 128, 43, 70, 65, 55, 6, 142, 174, 145, 16, 72, 155, 27, 9, 124, 175, 58, 109, 1, 30, 32, 25, 179, 45, 113, 141, 80, 177, 22, 83, 85, 37, 84, 90, 138, 153, 180, 134, 71, 87, 54, 164, 160, 7, 114, 78, 34, 11, 144, 93, 120, 66, 63, 168, 28, 110, 151, 86, 51, 44, 81, 64, 176, 98, 13, 24, 130, 171, 40, 17, 163, 94, 161, 57, 99, 106, 82, 2, 26, 79, 121, 102, 157, 129, 156, 69, 96, 46, 122, 19, 104, 56, 76, 0, 36, 167, 132, 73, 92, 107, 21, 117, 119, 108, 136, 159, 18, 181, 97, 166, 14, 74, 95, 137, 103, 12, 147, 152, 105, 133, 4, 41, 91, 125, 111, 62, 173, 149, 8, 89, 75, 146, 115, 60, 61, 170, 52, 154, 68, 139, 50, 20, 5, 33, 49, 35, 39, 15, 123, 169, 148, 31, 135, 47, 140, 67, 42, 38, 126, 101, 100, 143, 162, 150, 165, 29, 112, 182, 3, 172, 53, 23, 116],", "goal_raise_for_bs": 32}}